Workbook

Sheet 0_RFQ_RULES
A1: THE RATIFIED RFQ MECHANISM (operator entries cited; supersedes any older convention in later sheets)
A2: 1. Makers quote whole curves; fills split at each maker own price; no shared book (554/568)
A3: 2. You see SELF and AGGREGATE only (566)
A4: 3. PRICING = DORMANCY DIVIDER (606/607): aggregate = capital-weighted mean of maker mids, NO spread.
A5: Each maker bid/ask stands as posted; any quote crossing the divider is DORMANT (sleeps, not clipped).
A6: See sheet 2b_DIVIDER for the live calculation + checks.
A7: 4. LP inputs = exposure limits E+/E- ONLY, no notional, no leverage (604/607). See 8b_LP_LIMITS.
A8: 5. Bundle atomic: option/spread + carved perp open together, close IN FULL together (587).
A9: 6. Carved perp is still a perp in every respect (586).
A10: 7. Trader payout = option leg + perp leg. LP payout = OPTION LEG ONLY (592).
A11: 8. Close = a TRADE at the aggregate, closer own curve EXCLUDED; leverage never scales payout (578/592).
A12: 9. Account-level liquidation, ~50x, perps+options one pot, LP excluded; no per-position liq price.
... A14: the divider sheet shows the ratified multi-maker pricing on the same kernel.

Sheet 0_Inputs
A1: TEMPORAL — FULL LOOP ON THE BURR-2 KERNEL (edit yellow; all sheets recompute)
A3: CURVE (Burr-2 / t-family)
A4: S | B4: 65695.5 | C4: perp mark: the centre AND the crossing
A5: Sbar | B5: 0.6 | C5: LEVEL - sets the ATM price
A6: a | B6: 1.2705 | C6: shoulder sharpness near the money
A7: gam | B7: 1.8413 | C7: tail index
A8: kappa | B8: 0 | C8: THE state a swap moves (additive, clamp +-0.95)
A9: Npool | B9: 200 | C9: pool notional BTC
A10: lam | B10: 0.01 | C10: impact: kappa change per ATM trade = 1% of pool
A11: fee | B11: 0.003 | C11: flat fee off premium
A12: Bfn | B12: =EXP(GAMMALN(1/'0_Inputs'!$B$6)+GAMMALN('0_Inputs'!$B$7/'0_Inputs'!$B$6)-GAMMALN(1/'0_Inputs'!$B$6+'0_Inputs'!$B$7/'0_Inputs'!$B$6)) | C12: =B(1/a,gam/a) via GAMMALN
A13: sR | B13: ='0_Inputs'!$B$5*(1+'0_Inputs'!$B$8) | C13: call wing scale = Sbar(1+kappa)
A14: sL | B14: ='0_Inputs'!$B$5*(1-'0_Inputs'!$B$8) | C14: put wing scale = Sbar(1-kappa)
A15: G1_ | B15: =(1+(1/'0_Inputs'!$B$14)^'0_Inputs'!$B$6)^(-('0_Inputs'!$B$7+1)/'0_Inputs'!$B$6) | C15: put-wing survival at zero
A16: I1_ | B16: =('0_Inputs'!$B$14/'0_Inputs'!$B$6)*'0_Inputs'!$B$12*(1-BETADIST(1/(1+'0_Inputs'!$B$14^'0_Inputs'!$B$6),1/'0_Inputs'!$B$6,'0_Inputs'!$B$7/'0_Inputs'!$B$6)) | C16: put-wing integral at zero
A17: WR | B17: ='0_Inputs'!$B$13*'0_Inputs'!$B$12/'0_Inputs'!$B$6 | C17: call wing area
A18: WL | B18: =('0_Inputs'!$B$14*'0_Inputs'!$B$12/'0_Inputs'!$B$6-'0_Inputs'!$B$16-'0_Inputs'!$B$15)/(1-'0_Inputs'!$B$15) | C18: put wing area
A19: qR | B19: ='0_Inputs'!$B$18/('0_Inputs'!$B$17+'0_Inputs'!$B$18) | C19: THE PEG = WL/(WR+WL) - makes wings meet
A20: qL | B20: =1-'0_Inputs'!$B$19 | C20: =1-qR
A21: ATMp | B21: ='0_Inputs'!$B$19*('0_Inputs'!$B$13/'0_Inputs'!$B$6)*'0_Inputs'!$B$12 | C21: =qR*(sR/a)*Bfn
A23: PER-LP — own DEPTH (lambda_i) and own POSTED half-spread h_i
A24: LP | B24: lambda_i | C24: h_i posted | D24: depth cap (BTC) | E24: equity $
A25: LP-C tight | B25: 0.02 | C25: 0.0005 | D25: 60 | E25: 1000000
A26: LP-B mid | B26: 0.05 | C26: 0.0015 | D26: 40 | E26: 500000
A27: LP-A wide | B27: 0.1 | C27: 0.003 | D27: 100 | E27: 250000
A29: ACCOUNT / PERPS / CARVE (LP positions EXCLUDED from this account)
A30: club_long | B30: 4000000 | C30: all LONG perps, shared wallet
A31: club_short | B31: 3000000 | C31: all SHORT perps
A32: margin_frac | B32: 0.2 | C32: equity per $ notional
A33: carve_frac | B33: 0.25 | C33: fraction carved to back options
A34: acct_cap | B34: 50 | C34: ACCOUNT leverage cap
A35: mgn_per_unit | B35: 100000 | C35: $ per carved unit at close
A36: L0 | B36: 1 | C36: carved-slice scale
A37: RV | B37: 0.6 | C37: realized vol
A38: turn | B38: 0.3 | C38: turnover/day
A39: QN_volwtd | B39: 0.025 | C39: VOLUME-WEIGHTED avg trade size (fraction of pool). NOT the plain average: a few whales push this UP a lot. Revenue tracks THIS number.

Sheet 1_Curve
A1: THE BURR-2 CURVE — ONE number per strike; ITM by parity |k| + mirror wing
A3: k=K/S-1 | B3: uR | C3: uL | D3: A_call | E3: A_put | F3: CALL | G3: PUT | H3: C-P | I3: -k (must match) | J3: Gtilde (per strike)
A4: -0.6 | B4: =1/(1+('0_Inputs'!$B$13/MAX(ABS(A4),0.000000001))^'0_Inputs'!$B$6) | C4: =1/(1+('0_Inputs'!$B$14/MAX(ABS(A4),0.000000001))^'0_Inputs'!$B$6) | D4: ='0_Inputs'!$B$19*('0_Inputs'!$B$13/'0_Inputs'!$B$6)*'0_Inputs'!$B$12*(1-BETADIST(B4,1/'0_Inputs'!$B$6,'0_Inputs'!$B$7/'0_Inputs'!$B$6)) | E4: =IF(ABS(A4)>=1,0,'0_Inputs'!$B$20/(1-'0_Inputs'!$B$15)*(('0_Inputs'!$B$14/'0_Inputs'!$B$6)*'0_Inputs'!$B$12*(1-BETADIST(C4,1/'0_Inputs'!$B$6,'0_Inputs'!$B$7/'0_Inputs'!$B$6))-'0_Inputs'!$B$16-'0_Inputs'!$B$15*(1-ABS(A4)))) | F4: =IF(A4>=0,D4,-A4+E4) | G4: =IF(A4<=0,E4,A4+D4) | H4: =F4-G4 | I4: =-A4
A5: -0.4 | B5: =1/(1+('0_Inputs'!$B$13/MAX(ABS(A5),0.000000001))^'0_Inputs'!$B$6) | C5: =1/(1+('0_Inputs'!$B$14/MAX(ABS(A5),0.000000001))^'0_Inputs'!$B$6) | D5: ='0_Inputs'!$B$19*('0_Inputs'!$B$13/'0_Inputs'!$B$6)*'0_Inputs'!$B$12*(1-BETADIST(B5,1/'0_Inputs'!$B$6,'0_Inputs'!$B$7/'0_Inputs'!$B$6)) | E5: =IF(ABS(A5)>=1,0,'0_Inputs'!$B$20/(1-'0_Inputs'!$B$15)*(('0_Inputs'!$B$14/'0_Inputs'!$B$6)*'0_Inputs'!$B$12*(1-BETADIST(C5,1/'0_Inputs'!$B$6,'0_Inputs'!$B$7/'0_Inputs'!$B$6))-'0_Inputs'!$B$16-'0_Inputs'!$B$15*(1-ABS(A5)))) | F5: =IF(A5>=0,D5,-A5+E5) | G5: =IF(A5<=0,E5,A5+D5) | H5: =F5-G5 | I5: =-A5 | J5: =IFERROR(ABS(2*((A6-A5)*F4-(A6-A4)*F5+(A5-A4)*F6)/((A5-A4)*(A6-A5)*(A6-A4))*(1+A5)^2/MAX(F5,0.000001)),"")
A6: -0.25 | B6: =1/(1+('0_Inputs'!$B$13/MAX(ABS(A6),0.000000001))^'0_Inputs'!$B$6) | C6: =1/(1+('0_Inputs'!$B$14/MAX(ABS(A6),0.000000001))^'0_Inputs'!$B$6) | D6: ='0_Inputs'!$B$19*('0_Inputs'!$B$13/'0_Inputs'!$B$6)*'0_Inputs'!$B$12*(1-BETADIST(B6,1/'0_Inputs'!$B$6,'0_Inputs'!$B$7/'0_Inputs'!$B$6)) | E6: =IF(ABS(A6)>=1,0,'0_Inputs'!$B$20/(1-'0_Inputs'!$B$15)*(('0_Inputs'!$B$14/'0_Inputs'!$B$6)*'0_Inputs'!$B$12*(1-BETADIST(C6,1/'0_Inputs'!$B$6,'0_Inputs'!$B$7/'0_Inputs'!$B$6))-'0_Inputs'!$B$16-'0_Inputs'!$B$15*(1-ABS(A6)))) | F6: =IF(A6>=0,D6,-A6+E6) | G6: =IF(A6<=0,E6,A6+D6) | H6: =F6-G6 | I6: =-A6 | J6: =IFERROR(ABS(2*((A7-A6)*F5-(A7-A5)*F6+(A6-A5)*F7)/((A6-A5)*(A7-A6)*(A7-A5))*(1+A6)^2/MAX(F6,0.000001)),"")
A7: -0.15 | B7: =1/(1+('0_Inputs'!$B$13/MAX(ABS(A7),0.000000001))^'0_Inputs'!$B$6) | C7: =1/(1+('0_Inputs'!$B$14/MAX(ABS(A7),0.000000001))^'0_Inputs'!$B$6) | D7: ='0_Inputs'!$B$19*('0_Inputs'!$B$13/'0_Inputs'!$B$6)*'0_Inputs'!$B$12*(1-BETADIST(B7,1/'0_Inputs'!$B$6,'0_Inputs'!$B$7/'0_Inputs'!$B$6)) | E7: =IF(ABS(A7)>=1,0,'0_Inputs'!$B$20/(1-'0_Inputs'!$B$15)*(('0_Inputs'!$B$14/'0_Inputs'!$B$6)*'0_Inputs'!$B$12*(1-BETADIST(C7,1/'0_Inputs'!$B$6,'0_Inputs'!$B$7/'0_Inputs'!$B$6))-'0_Inputs'!$B$16-'0_Inputs'!$B$15*(1-ABS(A7)))) | F7: =IF(A7>=0,D7,-A7+E7) | G7: =IF(A7<=0,E7,A7+D7) | H7: =F7-G7 | I7: =-A7 | J7: =IFERROR(ABS(2*((A8-A7)*F6-(A8-A6)*F7+(A7-A6)*F8)/((A7-A6)*(A8-A7)*(A8-A6))*(1+A7)^2/MAX(F7,0.000001)),"")
A8: -0.05 | B8: =1/(1+('0_Inputs'!$B$13/MAX(ABS(A8),0.000000001))^'0_Inputs'!$B$6) | C8: =1/(1+('0_Inputs'!$B$14/MAX(ABS(A8),0.000000001))^'0_Inputs'!$B$6) | D8: ='0_Inputs'!$B$19*('0_Inputs'!$B$13/'0_Inputs'!$B$6)*'0_Inputs'!$B$12*(1-BETADIST(B8,1/'0_Inputs'!$B$6,'0_Inputs'!$B$7/'0_Inputs'!$B$6)) | E8: =IF(ABS(A8)>=1,0,'0_Inputs'!$B$20/(1-'0_Inputs'!$B$15)*(('0_Inputs'!$B$14/'0_Inputs'!$B$6)*'0_Inputs'!$B$12*(1-BETADIST(C8,1/'0_Inputs'!$B$6,'0_Inputs'!$B$7/'0_Inputs'!$B$6))-'0_Inputs'!$B$16-'0_Inputs'!$B$15*(1-ABS(A8)))) | F8: =IF(A8>=0,D8,-A8+E8) | G8: =IF(A8<=0,E8,A8+D8) | H8: =F8-G8 | I8: =-A8 | J8: =IFERROR(ABS(2*((A9-A8)*F7-(A9-A7)*F8+(A8-A7)*F9)/((A8-A7)*(A9-A8)*(A9-A7))*(1+A8)^2/MAX(F8,0.000001)),"")
A9: 0 | B9: =1/(1+('0_Inputs'!$B$13/MAX(ABS(A9),0.000000001))^'0_Inputs'!$B$6) | C9: =1/(1+('0_Inputs'!$B$14/MAX(ABS(A9),0.000000001))^'0_Inputs'!$B$6) | D9: ='0_Inputs'!$B$19*('0_Inputs'!$B$13/'0_Inputs'!$B$6)*'0_Inputs'!$B$12*(1-BETADIST(B9,1/'0_Inputs'!$B$6,'0_Inputs'!$B$7/'0_Inputs'!$B$6)) | E9: =IF(ABS(A9)>=1,0,'0_Inputs'!$B$20/(1-'0_Inputs'!$B$15)*(('0_Inputs'!$B$14/'0_Inputs'!$B$6)*'0_Inputs'!$B$12*(1-BETADIST(C9,1/'0_Inputs'!$B$6,'0_Inputs'!$B$7/'0_Inputs'!$B$6))-'0_Inputs'!$B$16-'0_Inputs'!$B$15*(1-ABS(A9)))) | F9: =IF(A9>=0,D9,-A9+E9) | G9: =IF(A9<=0,E9,A9+D9) | H9: =F9-G9 | I9: =-A9 | J9: =IFERROR(ABS(2*((A10-A9)*F8-(A10-A8)*F9+(A9-A8)*F10)/((A9-A8)*(A10-A9)*(A10-A8))*(1+A9)^2/MAX(F9,0.000001)),"")
A10: 0.05 | B10: =1/(1+('0_Inputs'!$B$13/MAX(ABS(A10),0.000000001))^'0_Inputs'!$B$6) | C10: =1/(1+('0_Inputs'!$B$14/MAX(ABS(A10),0.000000001))^'0_Inputs'!$B$6) | D10: ='0_Inputs'!$B$19*('0_Inputs'!$B$13/'0_Inputs'!$B$6)*'0_Inputs'!$B$12*(1-BETADIST(B10,1/'0_Inputs'!$B$6,'0_Inputs'!$B$7/'0_Inputs'!$B$6)) | E10: =IF(ABS(A10)>=1,0,'0_Inputs'!$B$20/(1-'0_Inputs'!$B$15)*(('0_Inputs'!$B$14/'0_Inputs'!$B$6)*'0_Inputs'!$B$12*(1-BETADIST(C10,1/'0_Inputs'!$B$6,'0_Inputs'!$B$7/'0_Inputs'!$B$6))-'0_Inputs'!$B$16-'0_Inputs'!$B$15*(1-ABS(A10)))) | F10: =IF(A10>=0,D10,-A10+E10) | G10: =IF(A10<=0,E10,A10+D10) | H10: =F10-G10 | I10: =-A10 | J10: =IFERROR(ABS(2*((A11-A10)*F9-(A11-A9)*F10+(A10-A9)*F11)/((A10-A9)*(A11-A10)*(A11-A9))*(1+A10)^2/MAX(F10,0.000001)),"")
A11: 0.15 | B11: =1/(1+('0_Inputs'!$B$13/MAX(ABS(A11),0.000000001))^'0_Inputs'!$B$6) | C11: =1/(1+('0_Inputs'!$B$14/MAX(ABS(A11),0.000000001))^'0_Inputs'!$B$6) | D11: ='0_Inputs'!$B$19*('0_Inputs'!$B$13/'0_Inputs'!$B$6)*'0_Inputs'!$B$12*(1-BETADIST(B11,1/'0_Inputs'!$B$6,'0_Inputs'!$B$7/'0_Inputs'!$B$6)) | E11: =IF(ABS(A11)>=1,0,'0_Inputs'!$B$20/(1-'0_Inputs'!$B$15)*(('0_Inputs'!$B$14/'0_Inputs'!$B$6)*'0_Inputs'!$B$12*(1-BETADIST(C11,1/'0_Inputs'!$B$6,'0_Inputs'!$B$7/'0_Inputs'!$B$6))-'0_Inputs'!$B$16-'0_Inputs'!$B$15*(1-ABS(A11)))) | F11: =IF(A11>=0,D11,-A11+E11) | G11: =IF(A11<=0,E11,A11+D11) | H11: =F11-G11 | I11: =-A11 | J11: =IFERROR(ABS(2*((A12-A11)*F10-(A12-A10)*F11+(A11-A10)*F12)/((A11-A10)*(A12-A11)*(A12-A10))*(1+A11)^2/MAX(F11,0.000001)),"")
A12: 0.25 | B12: =1/(1+('0_Inputs'!$B$13/MAX(ABS(A12),0.000000001))^'0_Inputs'!$B$6) | C12: =1/(1+('0_Inputs'!$B$14/MAX(ABS(A12),0.000000001))^'0_Inputs'!$B$6) | D12: ='0_Inputs'!$B$19*('0_Inputs'!$B$13/'0_Inputs'!$B$6)*'0_Inputs'!$B$12*(1-BETADIST(B12,1/'0_Inputs'!$B$6,'0_Inputs'!$B$7/'0_Inputs'!$B$6)) | E12: =IF(ABS(A12)>=1,0,'0_Inputs'!$B$20/(1-'0_Inputs'!$B$15)*(('0_Inputs'!$B$14/'0_Inputs'!$B$6)*'0_Inputs'!$B$12*(1-BETADIST(C12,1/'0_Inputs'!$B$6,'0_Inputs'!$B$7/'0_Inputs'!$B$6))-'0_Inputs'!$B$16-'0_Inputs'!$B$15*(1-ABS(A12)))) | F12: =IF(A12>=0,D12,-A12+E12) | G12: =IF(A12<=0,E12,A12+D12) | H12: =F12-G12 | I12: =-A12 | J12: =IFERROR(ABS(2*((A13-A12)*F11-(A13-A11)*F12+(A12-A11)*F13)/((A12-A11)*(A13-A12)*(A13-A11))*(1+A12)^2/MAX(F12,0.000001)),"")
A13: 0.4 | B13: =1/(1+('0_Inputs'!$B$13/MAX(ABS(A13),0.000000001))^'0_Inputs'!$B$6) | C13: =1/(1+('0_Inputs'!$B$14/MAX(ABS(A13),0.000000001))^'0_Inputs'!$B$6) | D13: ='0_Inputs'!$B$19*('0_Inputs'!$B$13/'0_Inputs'!$B$6)*'0_Inputs'!$B$12*(1-BETADIST(B13,1/'0_Inputs'!$B$6,'0_Inputs'!$B$7/'0_Inputs'!$B$6)) | E13: =IF(ABS(A13)>=1,0,'0_Inputs'!$B$20/(1-'0_Inputs'!$B$15)*(('0_Inputs'!$B$14/'0_Inputs'!$B$6)*'0_Inputs'!$B$12*(1-BETADIST(C13,1/'0_Inputs'!$B$6,'0_Inputs'!$B$7/'0_Inputs'!$B$6))-'0_Inputs'!$B$16-'0_Inputs'!$B$15*(1-ABS(A13)))) | F13: =IF(A13>=0,D13,-A13+E13) | G13: =IF(A13<=0,E13,A13+D13) | H13: =F13-G13 | I13: =-A13 | J13: =IFERROR(ABS(2*((A14-A13)*F12-(A14-A12)*F13+(A13-A12)*F14)/((A13-A12)*(A14-A13)*(A14-A12))*(1+A13)^2/MAX(F13,0.000001)),"")
A14: 0.6 | B14: =1/(1+('0_Inputs'!$B$13/MAX(ABS(A14),0.000000001))^'0_Inputs'!$B$6) | C14: =1/(1+('0_Inputs'!$B$14/MAX(ABS(A14),0.000000001))^'0_Inputs'!$B$6) | D14: ='0_Inputs'!$B$19*('0_Inputs'!$B$13/'0_Inputs'!$B$6)*'0_Inputs'!$B$12*(1-BETADIST(B14,1/'0_Inputs'!$B$6,'0_Inputs'!$B$7/'0_Inputs'!$B$6)) | E14: =IF(ABS(A14)>=1,0,'0_Inputs'!$B$20/(1-'0_Inputs'!$B$15)*(('0_Inputs'!$B$14/'0_Inputs'!$B$6)*'0_Inputs'!$B$12*(1-BETADIST(C14,1/'0_Inputs'!$B$6,'0_Inputs'!$B$7/'0_Inputs'!$B$6))-'0_Inputs'!$B$16-'0_Inputs'!$B$15*(1-ABS(A14)))) | F14: =IF(A14>=0,D14,-A14+E14) | G14: =IF(A14<=0,E14,A14+D14) | H14: =F14-G14 | I14: =-A14
J16: mean Gtilde
J17: =AVERAGE(J5:J13)
A18: Gtilde uses the UNEVEN-GRID 2nd-derivative formula (the strike grid is not equally spaced).
A19: It rises with |k| on the OTM side: wing inventory is far more expensive to carry than ATM.

Sheet 2_Quote
A1: TWO-SIDED QUOTE — CONTINUOUS (integral) execution: trader pays the AVERAGE along the path
A3: k | B3: mid (CALL) | C3: impact s_full | D3: posted h (tightest) | E3: effective half-spread (s_full/2) | F3: BID | G3: ASK | H3: round-trip %
A4: ='1_Curve'!A4 | B4: ='1_Curve'!F4 | C4: ='0_Inputs'!$B$10*('0_Inputs'!$B$39/0.01)*'0_Inputs'!$B$21/MAX(B4,0.000000001) | D4: =MIN('0_Inputs'!$C$25,'0_Inputs'!$C$26,'0_Inputs'!$C$27) | E4: =C4/2+D4 | F4: =B4*(1-E4) | G4: =B4*(1+E4) | H4: =2*E4
A5: ='1_Curve'!A5 | B5: ='1_Curve'!F5 | C5: ='0_Inputs'!$B$10*('0_Inputs'!$B$39/0.01)*'0_Inputs'!$B$21/MAX(B5,0.000000001) | D5: =MIN('0_Inputs'!$C$25,'0_Inputs'!$C$26,'0_Inputs'!$C$27) | E5: =C5/2+D5 | F5: =B5*(1-E5) | G5: =B5*(1+E5) | H5: =2*E5
A6: ='1_Curve'!A6 | B6: ='1_Curve'!F6 | C6: ='0_Inputs'!$B$10*('0_Inputs'!$B$39/0.01)*'0_Inputs'!$B$21/MAX(B6,0.000000001) | D6: =MIN('0_Inputs'!$C$25,'0_Inputs'!$C$26,'0_Inputs'!$C$27) | E6: =C6/2+D6 | F6: =B6*(1-E6) | G6: =B6*(1+E6) | H6: =2*E6
A7: ='1_Curve'!A7 | B7: ='1_Curve'!F7 | C7: ='0_Inputs'!$B$10*('0_Inputs'!$B$39/0.01)*'0_Inputs'!$B$21/MAX(B7,0.000000001) | D7: =MIN('0_Inputs'!$C$25,'0_Inputs'!$C$26,'0_Inputs'!$C$27) | E7: =C7/2+D7 | F7: =B7*(1-E7) | G7: =B7*(1+E7) | H7: =2*E7
A8: ='1_Curve'!A8 | B8: ='1_Curve'!F8 | C8: ='0_Inputs'!$B$10*('0_Inputs'!$B$39/0.01)*'0_Inputs'!$B$21/MAX(B8,0.000000001) | D8: =MIN('0_Inputs'!$C$25,'0_Inputs'!$C$26,'0_Inputs'!$C$27) | E8: =C8/2+D8 | F8: =B8*(1-E8) | G8: =B8*(1+E8) | H8: =2*E8
A9: ='1_Curve'!A9 | B9: ='1_Curve'!F9 | C9: ='0_Inputs'!$B$10*('0_Inputs'!$B$39/0.01)*'0_Inputs'!$B$21/MAX(B9,0.000000001) | D9: =MIN('0_Inputs'!$C$25,'0_Inputs'!$C$26,'0_Inputs'!$C$27) | E9: =C9/2+D9 | F9: =B9*(1-E9) | G9: =B9*(1+E9) | H9: =2*E9
A10: ='1_Curve'!A10 | B10: ='1_Curve'!F10 | C10: ='0_Inputs'!$B$10*('0_Inputs'!$B$39/0.01)*'0_Inputs'!$B$21/MAX(B10,0.000000001) | D10: =MIN('0_Inputs'!$C$25,'0_Inputs'!$C$26,'0_Inputs'!$C$27) | E10: =C10/2+D10 | F10: =B10*(1-E10) | G10: =B10*(1+E10) | H10: =2*E10
A11: ='1_Curve'!A11 | B11: ='1_Curve'!F11 | C11: ='0_Inputs'!$B$10*('0_Inputs'!$B$39/0.01)*'0_Inputs'!$B$21/MAX(B11,0.000000001) | D11: =MIN('0_Inputs'!$C$25,'0_Inputs'!$C$26,'0_Inputs'!$C$27) | E11: =C11/2+D11 | F11: =B11*(1-E11) | G11: =B11*(1+E11) | H11: =2*E11
A12: ='1_Curve'!A12 | B12: ='1_Curve'!F12 | C12: ='0_Inputs'!$B$10*('0_Inputs'!$B$39/0.01)*'0_Inputs'!$B$21/MAX(B12,0.000000001) | D12: =MIN('0_Inputs'!$C$25,'0_Inputs'!$C$26,'0_Inputs'!$C$27) | E12: =C12/2+D12 | F12: =B12*(1-E12) | G12: =B12*(1+E12) | H12: =2*E12
A13: ='1_Curve'!A13 | B13: ='1_Curve'!F13 | C13: ='0_Inputs'!$B$10*('0_Inputs'!$B$39/0.01)*'0_Inputs'!$B$21/MAX(B13,0.000000001) | D13: =MIN('0_Inputs'!$C$25,'0_Inputs'!$C$26,'0_Inputs'!$C$27) | E13: =C13/2+D13 | F13: =B13*(1-E13) | G13: =B13*(1+E13) | H13: =2*E13
A14: ='1_Curve'!A14 | B14: ='1_Curve'!F14 | C14: ='0_Inputs'!$B$10*('0_Inputs'!$B$39/0.01)*'0_Inputs'!$B$21/MAX(B14,0.000000001) | D14: =MIN('0_Inputs'!$C$25,'0_Inputs'!$C$26,'0_Inputs'!$C$27) | E14: =C14/2+D14 | F14: =B14*(1-E14) | G14: =B14*(1+E14) | H14: =2*E14
A16: INTEGRAL convention: the trader pays the AVERAGE price along the path (= half the full-size impact),
A17: NOT the post-execution price on the whole size. The impact half is a PRICE PATH, not LP revenue.

Sheet 3_Apportion
A1: LP APPORTIONMENT — closed form (depth-only) AND the ladder (posted spreads)
A3: A. CLOSED FORM (depth-only, same shape): 1/lam_agg = SUM(1/lam_i)
A4: LP | B4: lambda_i | C4: 1/lambda_i | D4: share w_i | E4: fill Q_i (BTC) | F4: revenue (BTC)
A5: ='0_Inputs'!A25 | B5: ='0_Inputs'!B25 | C5: =1/B5 | D5: =C5/SUM($C$5:$C$7) | E5: =D5*'0_Inputs'!$B$39*'0_Inputs'!$B$9 | F5: =D5*'2_Quote'!$E$9*'0_Inputs'!$B$39*'0_Inputs'!$B$9*'2_Quote'!$B$9
A6: ='0_Inputs'!A26 | B6: ='0_Inputs'!B26 | C6: =1/B6 | D6: =C6/SUM($C$5:$C$7) | E6: =D6*'0_Inputs'!$B$39*'0_Inputs'!$B$9 | F6: =D6*'2_Quote'!$E$9*'0_Inputs'!$B$39*'0_Inputs'!$B$9*'2_Quote'!$B$9
A7: ='0_Inputs'!A27 | B7: ='0_Inputs'!B27 | C7: =1/B7 | D7: =C7/SUM($C$5:$C$7) | E7: =D7*'0_Inputs'!$B$39*'0_Inputs'!$B$9 | F7: =D7*'2_Quote'!$E$9*'0_Inputs'!$B$39*'0_Inputs'!$B$9*'2_Quote'!$B$9
A8: lam_agg = 1/SUM(1/lam_i) | B8: =1/SUM(C5:C7)
A9: shares sum (must be 1) | D9: =SUM(D5:D7)
A10: revenue conserves? (apportioned - pool) | F10: =SUM(F5:F7)-'2_Quote'!$E$9*'0_Inputs'!$B$39*'0_Inputs'!$B$9*'2_Quote'!$B$9
A12: B. LADDER (required once POSTED SPREADS differ) — cheapest h fills first
A13: LP (by h) | B13: h_i | C13: depth cap | D13: cum. depth | E13: trade Q | F13: units filled | G13: own revenue
A14: ='0_Inputs'!A25 | B14: ='0_Inputs'!C25 | C14: ='0_Inputs'!D25 | D14: =SUM($C$14:C14) | E14: ='0_Inputs'!$B$39*'0_Inputs'!$B$9 | F14: =MAX(0,MIN(C14,$E$14-0)) | G14: =F14*B14*'2_Quote'!$B$9
A15: ='0_Inputs'!A26 | B15: ='0_Inputs'!C26 | C15: ='0_Inputs'!D26 | D15: =SUM($C$14:C15) | E15: ='0_Inputs'!$B$39*'0_Inputs'!$B$9 | F15: =MAX(0,MIN(C15,$E$14-D14)) | G15: =F15*B15*'2_Quote'!$B$9
A16: ='0_Inputs'!A27 | B16: ='0_Inputs'!C27 | C16: ='0_Inputs'!D27 | D16: =SUM($C$14:C16) | E16: ='0_Inputs'!$B$39*'0_Inputs'!$B$9 | F16: =MAX(0,MIN(C16,$E$14-D15)) | G16: =F16*B16*'2_Quote'!$B$9
A18: effective half-spread paid | G18: =IF(SUM(F14:F16)>0,SUMPRODUCT(F14:F16,B14:B16)/SUM(F14:F16),0)
A20: Closed form suffices ONLY for depth-only heterogeneity. Posted spread or shape => the ladder is load-bearing.
A22: C. LADDER ORDER IS NOT FIXED — it must be re-sorted per strike
A23: strike k | B23: cheapest LP here | C23: 2nd | D23: 3rd | E23: h of cheapest | F23: order changes?
A24: ='1_Curve'!A4 | B24: =INDEX({"LP-C","LP-B","LP-A"},MATCH(MIN('0_Inputs'!$C$25*(1+ABS(A24)*0),'0_Inputs'!$C$26*(1+ABS(A24)*1),'0_Inputs'!$C$27*(1+ABS(A24)*3)),{'0_Inputs'!$C$25*(1+ABS(A24)*0),'0_Inputs'!$C$26*(1+ABS(A24)*1),'0_Inputs'!$C$27*(1+ABS(A24)*3)},0)) | E24: =MIN('0_Inputs'!$C$25*(1+ABS(A24)*0),'0_Inputs'!$C$26*(1+ABS(A24)*1),'0_Inputs'!$C$27*(1+ABS(A24)*3)) | F24: =IF(B24=B$24,"same","CHANGED")
A25: ='1_Curve'!A5 | B25: =INDEX({"LP-C","LP-B","LP-A"},MATCH(MIN('0_Inputs'!$C$25*(1+ABS(A25)*0),'0_Inputs'!$C$26*(1+ABS(A25)*1),'0_Inputs'!$C$27*(1+ABS(A25)*3)),{'0_Inputs'!$C$25*(1+ABS(A25)*0),'0_Inputs'!$C$26*(1+ABS(A25)*1),'0_Inputs'!$C$27*(1+ABS(A25)*3)},0)) | E25: =MIN('0_Inputs'!$C$25*(1+ABS(A25)*0),'0_Inputs'!$C$26*(1+ABS(A25)*1),'0_Inputs'!$C$27*(1+ABS(A25)*3)) | F25: =IF(B25=B$24,"same","CHANGED")
A26: ='1_Curve'!A6 | B26: =INDEX({"LP-C","LP-B","LP-A"},MATCH(MIN('0_Inputs'!$C$25*(1+ABS(A26)*0),'0_Inputs'!$C$26*(1+ABS(A26)*1),'0_Inputs'!$C$27*(1+ABS(A26)*3)),{'0_Inputs'!$C$25*(1+ABS(A26)*0),'0_Inputs'!$C$26*(1+ABS(A26)*1),'0_Inputs'!$C$27*(1+ABS(A26)*3)},0)) | E26: =MIN('0_Inputs'!$C$25*(1+ABS(A26)*0),'0_Inputs'!$C$26*(1+ABS(A26)*1),'0_Inputs'!$C$27*(1+ABS(A26)*3)) | F26: =IF(B26=B$24,"same","CHANGED")
A27: ='1_Curve'!A7 | B27: =INDEX({"LP-C","LP-B","LP-A"},MATCH(MIN('0_Inputs'!$C$25*(1+ABS(A27)*0),'0_Inputs'!$C$26*(1+ABS(A27)*1),'0_Inputs'!$C$27*(1+ABS(A27)*3)),{'0_Inputs'!$C$25*(1+ABS(A27)*0),'0_Inputs'!$C$26*(1+ABS(A27)*1),'0_Inputs'!$C$27*(1+ABS(A27)*3)},0)) | E27: =MIN('0_Inputs'!$C$25*(1+ABS(A27)*0),'0_Inputs'!$C$26*(1+ABS(A27)*1),'0_Inputs'!$C$27*(1+ABS(A27)*3)) | F27: =IF(B27=B$24,"same","CHANGED")
A28: ='1_Curve'!A8 | B28: =INDEX({"LP-C","LP-B","LP-A"},MATCH(MIN('0_Inputs'!$C$25*(1+ABS(A28)*0),'0_Inputs'!$C$26*(1+ABS(A28)*1),'0_Inputs'!$C$27*(1+ABS(A28)*3)),{'0_Inputs'!$C$25*(1+ABS(A28)*0),'0_Inputs'!$C$26*(1+ABS(A28)*1),'0_Inputs'!$C$27*(1+ABS(A28)*3)},0)) | E28: =MIN('0_Inputs'!$C$25*(1+ABS(A28)*0),'0_Inputs'!$C$26*(1+ABS(A28)*1),'0_Inputs'!$C$27*(1+ABS(A28)*3)) | F28: =IF(B28=B$24,"same","CHANGED")
A29: ='1_Curve'!A9 | B29: =INDEX({"LP-C","LP-B","LP-A"},MATCH(MIN('0_Inputs'!$C$25*(1+ABS(A29)*0),'0_Inputs'!$C$26*(1+ABS(A29)*1),'0_Inputs'!$C$27*(1+ABS(A29)*3)),{'0_Inputs'!$C$25*(1+ABS(A29)*0),'0_Inputs'!$C$26*(1+ABS(A29)*1),'0_Inputs'!$C$27*(1+ABS(A29)*3)},0)) | E29: =MIN('0_Inputs'!$C$25*(1+ABS(A29)*0),'0_Inputs'!$C$26*(1+ABS(A29)*1),'0_Inputs'!$C$27*(1+ABS(A29)*3)) | F29: =IF(B29=B$24,"same","CHANGED")
A30: ='1_Curve'!A10 | B30: =INDEX({"LP-C","LP-B","LP-A"},MATCH(MIN('0_Inputs'!$C$25*(1+ABS(A30)*0),'0_Inputs'!$C$26*(1+ABS(A30)*1),'0_Inputs'!$C$27*(1+ABS(A30)*3)),{'0_Inputs'!$C$25*(1+ABS(A30)*0),'0_Inputs'!$C$26*(1+ABS(A30)*1),'0_Inputs'!$C$27*(1+ABS(A30)*3)},0)) | E30: =MIN('0_Inputs'!$C$25*(1+ABS(A30)*0),'0_Inputs'!$C$26*(1+ABS(A30)*1),'0_Inputs'!$C$27*(1+ABS(A30)*3)) | F30: =IF(B30=B$24,"same","CHANGED")
A31: ='1_Curve'!A11 | B31: =INDEX({"LP-C","LP-B","LP-A"},MATCH(MIN('0_Inputs'!$C$25*(1+ABS(A31)*0),'0_Inputs'!$C$26*(1+ABS(A31)*1),'0_Inputs'!$C$27*(1+ABS(A31)*3)),{'0_Inputs'!$C$25*(1+ABS(A31)*0),'0_Inputs'!$C$26*(1+ABS(A31)*1),'0_Inputs'!$C$27*(1+ABS(A31)*3)},0)) | E31: =MIN('0_Inputs'!$C$25*(1+ABS(A31)*0),'0_Inputs'!$C$26*(1+ABS(A31)*1),'0_Inputs'!$C$27*(1+ABS(A31)*3)) | F31: =IF(B31=B$24,"same","CHANGED")
A32: ='1_Curve'!A12 | B32: =INDEX({"LP-C","LP-B","LP-A"},MATCH(MIN('0_Inputs'!$C$25*(1+ABS(A32)*0),'0_Inputs'!$C$26*(1+ABS(A32)*1),'0_Inputs'!$C$27*(1+ABS(A32)*3)),{'0_Inputs'!$C$25*(1+ABS(A32)*0),'0_Inputs'!$C$26*(1+ABS(A32)*1),'0_Inputs'!$C$27*(1+ABS(A32)*3)},0)) | E32: =MIN('0_Inputs'!$C$25*(1+ABS(A32)*0),'0_Inputs'!$C$26*(1+ABS(A32)*1),'0_Inputs'!$C$27*(1+ABS(A32)*3)) | F32: =IF(B32=B$24,"same","CHANGED")
A33: ='1_Curve'!A13 | B33: =INDEX({"LP-C","LP-B","LP-A"},MATCH(MIN('0_Inputs'!$C$25*(1+ABS(A33)*0),'0_Inputs'!$C$26*(1+ABS(A33)*1),'0_Inputs'!$C$27*(1+ABS(A33)*3)),{'0_Inputs'!$C$25*(1+ABS(A33)*0),'0_Inputs'!$C$26*(1+ABS(A33)*1),'0_Inputs'!$C$27*(1+ABS(A33)*3)},0)) | E33: =MIN('0_Inputs'!$C$25*(1+ABS(A33)*0),'0_Inputs'!$C$26*(1+ABS(A33)*1),'0_Inputs'!$C$27*(1+ABS(A33)*3)) | F33: =IF(B33=B$24,"same","CHANGED")
A34: ='1_Curve'!A14 | B34: =INDEX({"LP-C","LP-B","LP-A"},MATCH(MIN('0_Inputs'!$C$25*(1+ABS(A34)*0),'0_Inputs'!$C$26*(1+ABS(A34)*1),'0_Inputs'!$C$27*(1+ABS(A34)*3)),{'0_Inputs'!$C$25*(1+ABS(A34)*0),'0_Inputs'!$C$26*(1+ABS(A34)*1),'0_Inputs'!$C$27*(1+ABS(A34)*3)},0)) | E34: =MIN('0_Inputs'!$C$25*(1+ABS(A34)*0),'0_Inputs'!$C$26*(1+ABS(A34)*1),'0_Inputs'!$C$27*(1+ABS(A34)*3)) | F34: =IF(B34=B$24,"same","CHANGED")
A36: Each LP's posted spread can vary with strike (h_i(k)). When it does, the cheapest LP CHANGES by strike,
A37: so the fill ladder must be re-sorted at every strike — a single fixed order is wrong. Column F flags where it changes.

Sheet 4_Trade
A1: THE SWAP — sell one wing, buy the other; the ONLY state it moves is kappa
A3: TRANSACTION
A4: SELL wing (+1 call, -1 put) | B4: 1
A5: SELL k | B5: 0.1
A6: SELL size Q (BTC) | B6: 5
A7: BUY wing | B7: -1
A8: BUY k | B8: -0.1
A10: LEG PRICES (from the Burr-2 curve)
A11: sell: uR | B11: =1/(1+('0_Inputs'!$B$13/MAX(ABS($B$5),0.000000001))^'0_Inputs'!$B$6)
A12: sell: uL | B12: =1/(1+('0_Inputs'!$B$14/MAX(ABS($B$5),0.000000001))^'0_Inputs'!$B$6)
A13: sell: A_call | B13: ='0_Inputs'!$B$19*('0_Inputs'!$B$13/'0_Inputs'!$B$6)*'0_Inputs'!$B$12*(1-BETADIST(B11,1/'0_Inputs'!$B$6,'0_Inputs'!$B$7/'0_Inputs'!$B$6))
A14: sell: A_put | B14: =IF(ABS($B$5)>=1,0,'0_Inputs'!$B$20/(1-'0_Inputs'!$B$15)*(('0_Inputs'!$B$14/'0_Inputs'!$B$6)*'0_Inputs'!$B$12*(1-BETADIST(B12,1/'0_Inputs'!$B$6,'0_Inputs'!$B$7/'0_Inputs'!$B$6))-'0_Inputs'!$B$16-'0_Inputs'!$B$15*(1-ABS($B$5))))
A15: sell: PRICE P_s | B15: =IF($B$4=1,IF($B$5>=0,B13,-$B$5+B14),IF($B$5<=0,B14,$B$5+B13))
A16: buy: uR | B16: =1/(1+('0_Inputs'!$B$13/MAX(ABS($B$8),0.000000001))^'0_Inputs'!$B$6)
A17: buy: uL | B17: =1/(1+('0_Inputs'!$B$14/MAX(ABS($B$8),0.000000001))^'0_Inputs'!$B$6)
A18: buy: A_call | B18: ='0_Inputs'!$B$19*('0_Inputs'!$B$13/'0_Inputs'!$B$6)*'0_Inputs'!$B$12*(1-BETADIST(B16,1/'0_Inputs'!$B$6,'0_Inputs'!$B$7/'0_Inputs'!$B$6))
A19: buy: A_put | B19: =IF(ABS($B$8)>=1,0,'0_Inputs'!$B$20/(1-'0_Inputs'!$B$15)*(('0_Inputs'!$B$14/'0_Inputs'!$B$6)*'0_Inputs'!$B$12*(1-BETADIST(B17,1/'0_Inputs'!$B$6,'0_Inputs'!$B$7/'0_Inputs'!$B$6))-'0_Inputs'!$B$16-'0_Inputs'!$B$15*(1-ABS($B$8))))
A20: buy: PRICE P_b | B20: =IF($B$7=1,IF($B$8>=0,B18,-$B$8+B19),IF($B$8<=0,B19,$B$8+B18))
A22: EXECUTION
A23: sell slippage s_s (INTEGRAL = half of full) | B23: =0.5*'0_Inputs'!$B$10*($B$6/'0_Inputs'!$B$9)/0.01*'0_Inputs'!$B$21/MAX(B15,0.000000001)
A24: proceeds V (BTC) | B24: =IF(B23>=1,0,$B$6*B15*(1-'0_Inputs'!$B$11)*(1-B23))
A25: first-pass buy size Q0 | B25: =IF(B20>0,B24/B20,0)
A26: buy slippage s_b (INTEGRAL) | B26: =0.5*'0_Inputs'!$B$10*(B25/'0_Inputs'!$B$9)/0.01*'0_Inputs'!$B$21/MAX(B20,0.000000001)
A27: BUY SIZE Q_b (the answer) | B27: =IF(OR(B23>=1,B26>=1),0,B24*(1-'0_Inputs'!$B$11)/(B20*(1+B26)))
A28: combined cost % | B28: =IFERROR(1-B27*B20/($B$6*B15),1)
A29: LP revenue this swap = FEE ONLY (impact is a price path, not revenue) | B29: =$B$6*B15*'0_Inputs'!$B$11+B27*B20*'0_Inputs'!$B$11
A30: (endpoint-convention revenue, for reference — the OLD overstated figure) | B30: =$B$6*B15-B27*B20
A31: STATE MOVE — kappa is the ONLY thing that changes
A32: delta kappa | B32: =-$B$4*'0_Inputs'!$B$10*($B$6/'0_Inputs'!$B$9)/0.01*'0_Inputs'!$B$21/MAX(B15,0.000000001)-$B$7*'0_Inputs'!$B$10*(B27/'0_Inputs'!$B$9)/0.01*'0_Inputs'!$B$21/MAX(B20,0.000000001)
A33: kappa AFTER (clamped) | B33: =MAX(-0.95,MIN(0.95,'0_Inputs'!$B$8+B32))
A34: sR after | B34: ='0_Inputs'!$B$5*(1+B33)
A35: sL after | B35: ='0_Inputs'!$B$5*(1-B33)
A37: A swap moves kappa -> the wings re-scale -> every strike re-prices. Level/shape (Sbar,a,gam) do NOT move.
A38: Impact moves the price along the path; the trader pays the integral. It is NOT captured as LP revenue.

Sheet 5_Portfolio
A1: PORTFOLIO ACCOUNTING — total value in ONE number (ITM by parity). No intrinsic/extrinsic split
A3: k | B3: side (+1 long) | C3: qty (BTC) | D3: unit value | E3: position value (BTC) | F3: in $
A4: 0.1 | B4: 1 | C4: 3 | D4: =IF(A4>=0,'1_Curve'!$D$4,'1_Curve'!$E$4)*0+IF(A4>=0,'0_Inputs'!$B$19*('0_Inputs'!$B$13/'0_Inputs'!$B$6)*'0_Inputs'!$B$12*(1-BETADIST(1/(1+('0_Inputs'!$B$13/MAX(ABS(A4),0.000000001))^'0_Inputs'!$B$6),1/'0_Inputs'!$B$6,'0_Inputs'!$B$7/'0_Inputs'!$B$6)),-A4+IF(ABS(A4)>=1,0,'0_Inputs'!$B$20/(1-'0_Inputs'!$B$15)*(('0_Inputs'!$B$14/'0_Inputs'!$B$6)*'0_Inputs'!$B$12*(1-BETADIST(1/(1+('0_Inputs'!$B$14/MAX(ABS(A4),0.000000001))^'0_Inputs'!$B$6),1/'0_Inputs'!$B$6,'0_Inputs'!$B$7/'0_Inputs'!$B$6))-'0_Inputs'!$B$16-'0_Inputs'!$B$15*(1-ABS(A4))))) | E4: =B4*C4*D4 | F4: =E4*'0_Inputs'!$B$4
A5: -0.1 | B5: -1 | C5: 2 | D5: =IF(A5>=0,'1_Curve'!$D$4,'1_Curve'!$E$4)*0+IF(A5>=0,'0_Inputs'!$B$19*('0_Inputs'!$B$13/'0_Inputs'!$B$6)*'0_Inputs'!$B$12*(1-BETADIST(1/(1+('0_Inputs'!$B$13/MAX(ABS(A5),0.000000001))^'0_Inputs'!$B$6),1/'0_Inputs'!$B$6,'0_Inputs'!$B$7/'0_Inputs'!$B$6)),-A5+IF(ABS(A5)>=1,0,'0_Inputs'!$B$20/(1-'0_Inputs'!$B$15)*(('0_Inputs'!$B$14/'0_Inputs'!$B$6)*'0_Inputs'!$B$12*(1-BETADIST(1/(1+('0_Inputs'!$B$14/MAX(ABS(A5),0.000000001))^'0_Inputs'!$B$6),1/'0_Inputs'!$B$6,'0_Inputs'!$B$7/'0_Inputs'!$B$6))-'0_Inputs'!$B$16-'0_Inputs'!$B$15*(1-ABS(A5))))) | E5: =B5*C5*D5 | F5: =E5*'0_Inputs'!$B$4
A6: 0.25 | B6: 1 | C6: 1.5 | D6: =IF(A6>=0,'1_Curve'!$D$4,'1_Curve'!$E$4)*0+IF(A6>=0,'0_Inputs'!$B$19*('0_Inputs'!$B$13/'0_Inputs'!$B$6)*'0_Inputs'!$B$12*(1-BETADIST(1/(1+('0_Inputs'!$B$13/MAX(ABS(A6),0.000000001))^'0_Inputs'!$B$6),1/'0_Inputs'!$B$6,'0_Inputs'!$B$7/'0_Inputs'!$B$6)),-A6+IF(ABS(A6)>=1,0,'0_Inputs'!$B$20/(1-'0_Inputs'!$B$15)*(('0_Inputs'!$B$14/'0_Inputs'!$B$6)*'0_Inputs'!$B$12*(1-BETADIST(1/(1+('0_Inputs'!$B$14/MAX(ABS(A6),0.000000001))^'0_Inputs'!$B$6),1/'0_Inputs'!$B$6,'0_Inputs'!$B$7/'0_Inputs'!$B$6))-'0_Inputs'!$B$16-'0_Inputs'!$B$15*(1-ABS(A6))))) | E6: =B6*C6*D6 | F6: =E6*'0_Inputs'!$B$4
A7: -0.3 | B7: 1 | C7: 1 | D7: =IF(A7>=0,'1_Curve'!$D$4,'1_Curve'!$E$4)*0+IF(A7>=0,'0_Inputs'!$B$19*('0_Inputs'!$B$13/'0_Inputs'!$B$6)*'0_Inputs'!$B$12*(1-BETADIST(1/(1+('0_Inputs'!$B$13/MAX(ABS(A7),0.000000001))^'0_Inputs'!$B$6),1/'0_Inputs'!$B$6,'0_Inputs'!$B$7/'0_Inputs'!$B$6)),-A7+IF(ABS(A7)>=1,0,'0_Inputs'!$B$20/(1-'0_Inputs'!$B$15)*(('0_Inputs'!$B$14/'0_Inputs'!$B$6)*'0_Inputs'!$B$12*(1-BETADIST(1/(1+('0_Inputs'!$B$14/MAX(ABS(A7),0.000000001))^'0_Inputs'!$B$6),1/'0_Inputs'!$B$6,'0_Inputs'!$B$7/'0_Inputs'!$B$6))-'0_Inputs'!$B$16-'0_Inputs'!$B$15*(1-ABS(A7))))) | E7: =B7*C7*D7 | F7: =E7*'0_Inputs'!$B$4
A9: TOTAL | E9: =SUM(E4:E7) | F9: =SUM(F4:F7)
A11: Every leg is ONE number off the curve: OTM = wing, ITM = |k| + mirror wing. Nothing is split.

Sheet 6_Perps_Account
A1: PERPS -> CARVE -> OPTIONS -> ACCOUNT-LEVEL LIQUIDATION (LP excluded)
A3: line | B3: LONG club | C3: SHORT club | D3: TOTAL
A4: perp notional $ | B4: ='0_Inputs'!$B$30 | C4: ='0_Inputs'!$B$31 | D4: =B4+C4
A5: account equity $ | B5: =B4*'0_Inputs'!$B$32 | C5: =C4*'0_Inputs'!$B$32 | D5: =B5+C5
A6: CARVE: notional carved to back options | B6: =B4*'0_Inputs'!$B$33 | C6: =C4*'0_Inputs'!$B$33 | D6: =B6+C6
A7: equity carved out of perps tab | B7: =B6*'0_Inputs'!$B$32 | C7: =C6*'0_Inputs'!$B$32 | D7: =B7+C7
A8: perps tab after carve (equity) | B8: =B5-B7 | C8: =C5-C7 | D8: =B8+C8
A9: options position value $ (from 5_Portfolio) | B9: ='5_Portfolio'!$F$9/2 | C9: ='5_Portfolio'!$F$9/2 | D9: =B9+C9
A10: ACCOUNT gross notional (perps + options) | B10: =B4+ABS(B9) | C10: =C4+ABS(C9) | D10: =B10+C10
A11: ACCOUNT equity (one pot: perps + options) | B11: =B5+B9 | C11: =C5+C9 | D11: =B11+C11
A12: ACCOUNT leverage | B12: =B10/B11 | C12: =C10/C11 | D12: =B12+C12
A14: LIQUIDATED? | B14: =IF(MAX(B12,C12)>'0_Inputs'!$B$34,"YES - ACCOUNT LIQUIDATES","NO - within cap")

Sheet 7_Margin
A1: LAYER 3 — PERP UNITS -> ACTUAL MARGIN (the one doorway)
A3: line | B3: value
A4: net position value in PERP UNITS (BTC) | B4: ='5_Portfolio'!$E$9
A5: x margin per unit $ | B5: ='0_Inputs'!$B$35
A6: x L0 | B6: ='0_Inputs'!$B$36
A7: =MARGIN / CASH $ (the doorway) | B7: =B4*B5*B6
A9: Perp-land -> cash-land happens ONCE, at the exit.

Sheet 8_LP_Econ
A1: LP ECONOMICS ON THE BURR-2 KERNEL — revenue (fee+impact) vs gamma bleed
A3: line | B3: LP-C | C3: LP-B | D3: LP-A | E3: TOTAL
A4: share w_i (depth-only) | B4: ='3_Apportion'!D5 | C4: ='3_Apportion'!D6 | D4: ='3_Apportion'!D7 | E4: =SUM(B4:D4)
A5: book value share $ | B5: =B4*'5_Portfolio'!$F$9 | C5: =C4*'5_Portfolio'!$F$9 | D5: =D4*'5_Portfolio'!$F$9 | E5: =SUM(B5:D5)
A6: revenue/yr = FEE x VOLUME only (BTC) | B6: =B4*'0_Inputs'!$B$11*'0_Inputs'!$B$38*365*'5_Portfolio'!$E$9 | C6: =C4*'0_Inputs'!$B$11*'0_Inputs'!$B$38*365*'5_Portfolio'!$E$9 | D6: =D4*'0_Inputs'!$B$11*'0_Inputs'!$B$38*365*'5_Portfolio'!$E$9 | E6: =SUM(B6:D6)
A7: revenue/yr $ | B7: =B6*'0_Inputs'!$B$4 | C7: =C6*'0_Inputs'!$B$4 | D7: =D6*'0_Inputs'!$B$4 | E7: =SUM(B7:D7)
A8: Gtilde (curvature per unit value) | B8: ='1_Curve'!$J$17 | C8: ='1_Curve'!$J$17 | D8: ='1_Curve'!$J$17 | E8: =SUM(B8:D8)
A9: gamma bleed/yr $ | B9: =0.5*B8*'0_Inputs'!$B$37^2*ABS(B5) | C9: =0.5*C8*'0_Inputs'!$B$37^2*ABS(C5) | D9: =0.5*D8*'0_Inputs'!$B$37^2*ABS(D5) | E9: =SUM(B9:D9)
A10: NET $/yr | B10: =B7-B9 | C10: =C7-C9 | D10: =D7-D9 | E10: =SUM(B10:D10)
A11: equity $ | B11: ='0_Inputs'!$E$25 | C11: ='0_Inputs'!$E$26 | D11: ='0_Inputs'!$E$27 | E11: =SUM(B11:D11)
A12: NET APR | B12: =B10/B11 | C12: =C10/C11 | D12: =D10/D11 | E12: =E10/E11
A14: Gtilde now READ LIVE from 1_Curve!J17 (mean of the per-strike column), not hard-coded. It rises with |k|.
A15: NOTE: an LP concentrated in the wings faces a HIGHER Gtilde than this mean; per-LP strike mix is the next refinement.
A16: Revenue is fee x VOLUME. Trade SIZE does not enter (integral convention). Impact is not revenue.

Sheet 9_CHECKS
A1: CHECKS — every invariant of the Burr-2 loop in one place
A3: check | B3: value | C3: want | D3: what it proves
A4: B1 put-call parity C-P = -k (max abs error) | B4: =MAX(ABS('1_Curve'!H4-'1_Curve'!I4),ABS('1_Curve'!H8-'1_Curve'!I8),ABS('1_Curve'!H14-'1_Curve'!I14)) | C4: <1e-9 | D4: the ITM extension is exact
A5: B2 ATM wings meet: A_call(0) = A_put(0) | B5: ='1_Curve'!D9-'1_Curve'!E9 | C5: =0 | D5: the peg qR=WL/(WR+WL) works
A6: B3 ATM price = ATMp input | B6: ='1_Curve'!F9-'0_Inputs'!$B$21 | C6: =0 | D6: curve ties to the header
A7: B4 qR + qL = 1 | B7: ='0_Inputs'!$B$19+'0_Inputs'!$B$20-1 | C7: =0 | D7: peg normalisation
A8: B5 apportionment shares sum to 1 | B8: ='3_Apportion'!D9-1 | C8: =0 | D8: allocation is exhaustive
A9: B6 apportionment revenue conserves | B9: ='3_Apportion'!F10 | C9: ~0 | D9: no value created/lost in the split
A10: B7 round-trip cost > 0 (irreversible) | B10: ='2_Quote'!H9 | C10: >0 | D10: impact IS revenue, not reversible slippage
A11: B8 swap moves kappa | B11: ='4_Trade'!B32 | C11: <>0 | D11: the swap changes the ONLY state it should
A12: B9 kappa stays in (-0.95, 0.95) | B12: =MIN(0.95-ABS('4_Trade'!B33),1) | C12: >0 | D12: clamp respected
A13: B10 LP revenue on the swap > 0 | B13: ='4_Trade'!B29 | C13: >0 | D13: the pool captures on the round leg
A14: B11 account leverage under cap | B14: ='0_Inputs'!$B$34-MAX('6_Perps_Account'!B12,'6_Perps_Account'!C12) | C14: >0 | D14: no liquidation now
A15: B12 margin doorway ties to portfolio | B15: ='7_Margin'!B7-'5_Portfolio'!E9*'0_Inputs'!$B$35*'0_Inputs'!$B$36 | C15: =0 | D15: units->cash is the single doorway
A16: B13 LP net APR (viability) | B16: ='8_LP_Econ'!E12 | C16: >0 | D16: revenue beats the gamma bleed
A17: B14 break-even avg trade size Q/N | B17: =('0_Inputs'!$B$37^2*0.5*5.76/('0_Inputs'!$B$38*365)-'0_Inputs'!$B$11)/(0.5*'0_Inputs'!$B$10/0.01*'0_Inputs'!$B$21/'2_Quote'!$B$9) | C17: vs QN input | D17: THE viability lever: trade size
A19: B14 vs the QN input on 0_Inputs is the viability test: if required Q/N > actual, LPs lose money.

Sheet 10_Viability
A1: VIABILITY — fee x turnover (integral convention: revenue = fee x volume)
A3: gamma bleed / yr (per unit book value) | B3: =0.5*'1_Curve'!$J$17*'0_Inputs'!$B$37^2
A5: NET (revenue - bleed), x book value/yr
A6: fee (bps) \ turnover/day | B6: 0.1 | C6: 0.3 | D6: 0.5 | E6: 1 | F6: 2 | G6: 3 | H6: 5
A7: 10 | B7: =$A7/10000*B$6*365-$B$3 | C7: =$A7/10000*C$6*365-$B$3 | D7: =$A7/10000*D$6*365-$B$3 | E7: =$A7/10000*E$6*365-$B$3 | F7: =$A7/10000*F$6*365-$B$3 | G7: =$A7/10000*G$6*365-$B$3 | H7: =$A7/10000*H$6*365-$B$3
A8: 30 | B8: =$A8/10000*B$6*365-$B$3 | C8: =$A8/10000*C$6*365-$B$3 | D8: =$A8/10000*D$6*365-$B$3 | E8: =$A8/10000*E$6*365-$B$3 | F8: =$A8/10000*F$6*365-$B$3 | G8: =$A8/10000*G$6*365-$B$3 | H8: =$A8/10000*H$6*365-$B$3
A9: 50 | B9: =$A9/10000*B$6*365-$B$3 | C9: =$A9/10000*C$6*365-$B$3 | D9: =$A9/10000*D$6*365-$B$3 | E9: =$A9/10000*E$6*365-$B$3 | F9: =$A9/10000*F$6*365-$B$3 | G9: =$A9/10000*G$6*365-$B$3 | H9: =$A9/10000*H$6*365-$B$3
A10: 75 | B10: =$A10/10000*B$6*365-$B$3 | C10: =$A10/10000*C$6*365-$B$3 | D10: =$A10/10000*D$6*365-$B$3 | E10: =$A10/10000*E$6*365-$B$3 | F10: =$A10/10000*F$6*365-$B$3 | G10: =$A10/10000*G$6*365-$B$3 | H10: =$A10/10000*H$6*365-$B$3
A11: 100 | B11: =$A11/10000*B$6*365-$B$3 | C11: =$A11/10000*C$6*365-$B$3 | D11: =$A11/10000*D$6*365-$B$3 | E11: =$A11/10000*E$6*365-$B$3 | F11: =$A11/10000*F$6*365-$B$3 | G11: =$A11/10000*G$6*365-$B$3 | H11: =$A11/10000*H$6*365-$B$3
A12: 150 | B12: =$A12/10000*B$6*365-$B$3 | C12: =$A12/10000*C$6*365-$B$3 | D12: =$A12/10000*D$6*365-$B$3 | E12: =$A12/10000*E$6*365-$B$3 | F12: =$A12/10000*F$6*365-$B$3 | G12: =$A12/10000*G$6*365-$B$3 | H12: =$A12/10000*H$6*365-$B$3
A13: 200 | B13: =$A13/10000*B$6*365-$B$3 | C13: =$A13/10000*C$6*365-$B$3 | D13: =$A13/10000*D$6*365-$B$3 | E13: =$A13/10000*E$6*365-$B$3 | F13: =$A13/10000*F$6*365-$B$3 | G13: =$A13/10000*G$6*365-$B$3 | H13: =$A13/10000*H$6*365-$B$3
A16: green = LP profitable. Break-even fee at a given turnover: fee = bleed/(turnover x 365).
A17: TODAY: 30bps at 0.3x/day = deep red. You need ~90bps at 0.3x, or ~0.9x/day at 30bps.

Sheet 2b_DIVIDER
A1: DORMANCY DIVIDER — 4 makers, one strike (edit blue)
A3: maker | B3: capital | C3: mid quote C_i(k) | D3: ask=C*(1+h) | E3: bid=C*(1-h)
A4: you | B4: 95 | C4: 0.1354 | D4: =C4*(1+$B$10/10000) | E4: =C4*(1-$B$10/10000)
A5: a | B5: 38 | C5: 0.1259 | D5: =C5*(1+$B$10/10000) | E5: =C5*(1-$B$10/10000)
A6: b | B6: 19 | C6: 0.142 | D6: =C6*(1+$B$10/10000) | E6: =C6*(1-$B$10/10000)
A7: c | B7: 48 | C7: 0.1371 | D7: =C7*(1+$B$10/10000) | E7: =C7*(1-$B$10/10000)
A10: half-spread h (bps) | B10: 19
A12: DIVIDER = capital-weighted mean of mids | B12: =SUMPRODUCT(B4:B7,C4:C7)/SUM(B4:B7)
A13: effective ASK = min ask >= divider | B13: =MINIFS(D4:D7,D4:D7,">="&B12)
A14: effective BID = max bid <= divider | B14: =MAXIFS(E4:E7,E4:E7,"<="&B12)
A15: asks dormant (below divider) | B15: =COUNTIF(D4:D7,"<"&B12)
A16: bids dormant (above divider) | B16: =COUNTIF(E4:E7,">"&B12)
A18: CHECKS
A19: never crossed: effAsk >= divider >= effBid | B19: =IF(AND(B13>=B12,B12>=B14),"PASS","FAIL")
A20: ask side alive (dearest maker survives) | B20: =IF(B13<>"","PASS","FAIL")
A21: bid side alive (cheapest maker survives) | B21: =IF(B14<>"","PASS","FAIL")
A22: every fill at a REAL posted quote | B22: =IF(OR(B13=D4,B13=D5,B13=D6,B13=D7),"PASS","FAIL")

Sheet 8b_LP_LIMITS
A1: LP FROM EXPOSURE LIMITS ONLY (604/607) — no notional, no leverage input
A3: long limit E+ | B3: 60
A4: short limit E- | B4: -40
A5: current exposure e | B5: 10
A6: tilt max t_max | B6: 0.08
A7: S-bar base (oracle) | B7: 0.6
A9: N_bid = max(0,E+ - e) | B9: =MAX(0,B3-B5)
A10: N_ask = max(0,e - E-) | B10: =MAX(0,B5-B4)
A11: tilt = -t_max*(e-mid)/half | B11: =-B6*((B5-(B3+B4)/2)/((B3-B4)/2))
A12: S-bar effective | B12: =B7*(1+B11)
A14: CHECK: depth split constant = E+ - E- | B14: =IF(ABS((B9+B10)-(B3-B4))<0.000001,"PASS","FAIL")
