Workbook

Sheet READ_ME
A1: Temporal LP economics — options-seller model (v5, calibrated + execution costs) — BRAINSTORM / non-core
A2: The LP SELLS the perpetual-option book (bands), delta-hedged on HL ⇒ SHORT-VOL. Premium IS the funding (perpetual carry).
A3: Edge = carry (priced at the CALIBRATION vol) minus the realized-vol gamma bleed. Profits when realized vol < calibration vol.
A5: MODEL (per $ equity, annualized):
A6: G = (m*gamma)*(m*gamma+1)/2 lensed gamma factor (m is in it)
A7: Carry income = +LP_leverage*G*sigma_cal^2 (the funding the LP collects)
A8: Vol cost = -LP_leverage*G*RV^2 (the LVR-EQUIVALENT gamma bleed — RISK 1)
A9: options_net = Carry + Vol cost = LP_leverage*G*(sigma_cal^2 - RV^2)
A10: BASE = options_net + fees - financing - (hedge_exec_cost + order_mgmt_cost)*LP_leverage + LP_leverage*hedge_funding_APR
A11: RESTAKED = BASE + HLP_base_APR*(1 - HLP_tail_haircut*RV)
A13: THE TWO VOL RISKS (operator entry 496 #4):
A14: RISK 1 = the vol cost itself (gamma bleed at realized vol) — the LVR-equivalent, always there.
... A21: STILL OPEN: carry magnitude assumes funding=fair carry (real law=update-2); cost defaults are ESTIMATES; reduced-form, non-core.

Sheet Assumptions
A1: EDITABLE ASSUMPTIONS (edit yellow cells)
A3: Assumption | B3: Value | C3: Disclosure / note
A4: days_per_year | B4: 365 | C4: annualization
A5: gamma_curve | B5: 2 | C5: base gamma of value∝S^(-gamma).
A6: m_steepness | B6: 1 | C6: steepness knob; lensed exponent m*gamma; enters G=(m*gamma)(m*gamma+1)/2.
A7: LP_leverage | B7: 1 | C7: leverage on the Temporal/options side (option value short per $ equity; 1x=unlevered). HLP NOT levered.
A8: daily_turnover | B8: 0.3 | C8: volume/notional per day (entry 496 #2: 100% unlikely; 0.2-0.4x realistic).
A9: fee_bps | B9: 2.5 | C9: taker fee, bps of notional (entry 496 #3: 2.5bps likely).
A10: borrow_APR | B10: 0.06 | C10: financing on the (LP_leverage-1) leg.
A11: hedge_exec_cost | B11: 0.01 | C11: IMPERFECT delta hedge + execution slippage, APR (entry 496 #1). Estimate.
A12: order_mgmt_cost | B12: 0.005 | C12: constant limit-order placement/cancel/update on HL, APR (entry 496 #5). Estimate.
A13: hedge_funding_APR | B13: 0 | C13: funding on the HL hedge legs, +/- (default 0).
A14: HLP_base_APR | B14: 0.1 | C14: yield on HLP margin (additive, NOT levered).
A15: HLP_tail_haircut | B15: 0 | C15: 0=pure additive; >0 shaves HLP as RV rises.
A16: Grid axes (editable):
A17: realized_vol RV (ROWS) -> | B17: 0.2 | C17: 0.4 | D17: 0.6 | E17: 0.8 | F17: 1
A18: sigma_cal calibration vol (COLS) -> | B18: 0.3 | C18: 0.5 | D18: 0.7 | E18: 0.9 | F18: 1.1

Sheet Regime_Grid
A1: REGIME GRID — net LP yield APR. rows=REALIZED vol, cols=CALIBRATION vol. green=profit / red=loss.
A3: BASE — options-seller LP net APR (dollar margin).
A4: RV \ sigma_cal | B4: =Assumptions!B$18 | C4: =Assumptions!C$18 | D4: =Assumptions!D$18 | E4: =Assumptions!E$18 | F4: =Assumptions!F$18
A5: =Assumptions!B$17 | B5: =Assumptions!$B$7*((Assumptions!$B$6*Assumptions!$B$5)*((Assumptions!$B$6*Assumptions!$B$5)+1)/2)*((B$4)^2-($A5)^2)-(Assumptions!$B$7-1)*Assumptions!$B$10-(Assumptions!$B$11+Assumptions!$B$12)*Assumptions!$B$7+Assumptions!$B$7*Assumptions!$B$13+Assumptions!$B$9/10000*Assumptions!$B$8*Assumptions!$B$4*Assumptions!$B$7 | C5: =Assumptions!$B$7*((Assumptions!$B$6*Assumptions!$B$5)*((Assumptions!$B$6*Assumptions!$B$5)+1)/2)*((C$4)^2-($A5)^2)-(Assumptions!$B$7-1)*Assumptions!$B$10-(Assumptions!$B$11+Assumptions!$B$12)*Assumptions!$B$7+Assumptions!$B$7*Assumptions!$B$13+Assumptions!$B$9/10000*Assumptions!$B$8*Assumptions!$B$4*Assumptions!$B$7 | D5: =Assumptions!$B$7*((Assumptions!$B$6*Assumptions!$B$5)*((Assumptions!$B$6*Assumptions!$B$5)+1)/2)*((D$4)^2-($A5)^2)-(Assumptions!$B$7-1)*Assumptions!$B$10-(Assumptions!$B$11+Assumptions!$B$12)*Assumptions!$B$7+Assumptions!$B$7*Assumptions!$B$13+Assumptions!$B$9/10000*Assumptions!$B$8*Assumptions!$B$4*Assumptions!$B$7 | E5: =Assumptions!$B$7*((Assumptions!$B$6*Assumptions!$B$5)*((Assumptions!$B$6*Assumptions!$B$5)+1)/2)*((E$4)^2-($A5)^2)-(Assumptions!$B$7-1)*Assumptions!$B$10-(Assumptions!$B$11+Assumptions!$B$12)*Assumptions!$B$7+Assumptions!$B$7*Assumptions!$B$13+Assumptions!$B$9/10000*Assumptions!$B$8*Assumptions!$B$4*Assumptions!$B$7 | F5: =Assumptions!$B$7*((Assumptions!$B$6*Assumptions!$B$5)*((Assumptions!$B$6*Assumptions!$B$5)+1)/2)*((F$4)^2-($A5)^2)-(Assumptions!$B$7-1)*Assumptions!$B$10-(Assumptions!$B$11+Assumptions!$B$12)*Assumptions!$B$7+Assumptions!$B$7*Assumptions!$B$13+Assumptions!$B$9/10000*Assumptions!$B$8*Assumptions!$B$4*Assumptions!$B$7
A6: =Assumptions!C$17 | B6: =Assumptions!$B$7*((Assumptions!$B$6*Assumptions!$B$5)*((Assumptions!$B$6*Assumptions!$B$5)+1)/2)*((B$4)^2-($A6)^2)-(Assumptions!$B$7-1)*Assumptions!$B$10-(Assumptions!$B$11+Assumptions!$B$12)*Assumptions!$B$7+Assumptions!$B$7*Assumptions!$B$13+Assumptions!$B$9/10000*Assumptions!$B$8*Assumptions!$B$4*Assumptions!$B$7 | C6: =Assumptions!$B$7*((Assumptions!$B$6*Assumptions!$B$5)*((Assumptions!$B$6*Assumptions!$B$5)+1)/2)*((C$4)^2-($A6)^2)-(Assumptions!$B$7-1)*Assumptions!$B$10-(Assumptions!$B$11+Assumptions!$B$12)*Assumptions!$B$7+Assumptions!$B$7*Assumptions!$B$13+Assumptions!$B$9/10000*Assumptions!$B$8*Assumptions!$B$4*Assumptions!$B$7 | D6: =Assumptions!$B$7*((Assumptions!$B$6*Assumptions!$B$5)*((Assumptions!$B$6*Assumptions!$B$5)+1)/2)*((D$4)^2-($A6)^2)-(Assumptions!$B$7-1)*Assumptions!$B$10-(Assumptions!$B$11+Assumptions!$B$12)*Assumptions!$B$7+Assumptions!$B$7*Assumptions!$B$13+Assumptions!$B$9/10000*Assumptions!$B$8*Assumptions!$B$4*Assumptions!$B$7 | E6: =Assumptions!$B$7*((Assumptions!$B$6*Assumptions!$B$5)*((Assumptions!$B$6*Assumptions!$B$5)+1)/2)*((E$4)^2-($A6)^2)-(Assumptions!$B$7-1)*Assumptions!$B$10-(Assumptions!$B$11+Assumptions!$B$12)*Assumptions!$B$7+Assumptions!$B$7*Assumptions!$B$13+Assumptions!$B$9/10000*Assumptions!$B$8*Assumptions!$B$4*Assumptions!$B$7 | F6: =Assumptions!$B$7*((Assumptions!$B$6*Assumptions!$B$5)*((Assumptions!$B$6*Assumptions!$B$5)+1)/2)*((F$4)^2-($A6)^2)-(Assumptions!$B$7-1)*Assumptions!$B$10-(Assumptions!$B$11+Assumptions!$B$12)*Assumptions!$B$7+Assumptions!$B$7*Assumptions!$B$13+Assumptions!$B$9/10000*Assumptions!$B$8*Assumptions!$B$4*Assumptions!$B$7
A7: =Assumptions!D$17 | B7: =Assumptions!$B$7*((Assumptions!$B$6*Assumptions!$B$5)*((Assumptions!$B$6*Assumptions!$B$5)+1)/2)*((B$4)^2-($A7)^2)-(Assumptions!$B$7-1)*Assumptions!$B$10-(Assumptions!$B$11+Assumptions!$B$12)*Assumptions!$B$7+Assumptions!$B$7*Assumptions!$B$13+Assumptions!$B$9/10000*Assumptions!$B$8*Assumptions!$B$4*Assumptions!$B$7 | C7: =Assumptions!$B$7*((Assumptions!$B$6*Assumptions!$B$5)*((Assumptions!$B$6*Assumptions!$B$5)+1)/2)*((C$4)^2-($A7)^2)-(Assumptions!$B$7-1)*Assumptions!$B$10-(Assumptions!$B$11+Assumptions!$B$12)*Assumptions!$B$7+Assumptions!$B$7*Assumptions!$B$13+Assumptions!$B$9/10000*Assumptions!$B$8*Assumptions!$B$4*Assumptions!$B$7 | D7: =Assumptions!$B$7*((Assumptions!$B$6*Assumptions!$B$5)*((Assumptions!$B$6*Assumptions!$B$5)+1)/2)*((D$4)^2-($A7)^2)-(Assumptions!$B$7-1)*Assumptions!$B$10-(Assumptions!$B$11+Assumptions!$B$12)*Assumptions!$B$7+Assumptions!$B$7*Assumptions!$B$13+Assumptions!$B$9/10000*Assumptions!$B$8*Assumptions!$B$4*Assumptions!$B$7 | E7: =Assumptions!$B$7*((Assumptions!$B$6*Assumptions!$B$5)*((Assumptions!$B$6*Assumptions!$B$5)+1)/2)*((E$4)^2-($A7)^2)-(Assumptions!$B$7-1)*Assumptions!$B$10-(Assumptions!$B$11+Assumptions!$B$12)*Assumptions!$B$7+Assumptions!$B$7*Assumptions!$B$13+Assumptions!$B$9/10000*Assumptions!$B$8*Assumptions!$B$4*Assumptions!$B$7 | F7: =Assumptions!$B$7*((Assumptions!$B$6*Assumptions!$B$5)*((Assumptions!$B$6*Assumptions!$B$5)+1)/2)*((F$4)^2-($A7)^2)-(Assumptions!$B$7-1)*Assumptions!$B$10-(Assumptions!$B$11+Assumptions!$B$12)*Assumptions!$B$7+Assumptions!$B$7*Assumptions!$B$13+Assumptions!$B$9/10000*Assumptions!$B$8*Assumptions!$B$4*Assumptions!$B$7
A8: =Assumptions!E$17 | B8: =Assumptions!$B$7*((Assumptions!$B$6*Assumptions!$B$5)*((Assumptions!$B$6*Assumptions!$B$5)+1)/2)*((B$4)^2-($A8)^2)-(Assumptions!$B$7-1)*Assumptions!$B$10-(Assumptions!$B$11+Assumptions!$B$12)*Assumptions!$B$7+Assumptions!$B$7*Assumptions!$B$13+Assumptions!$B$9/10000*Assumptions!$B$8*Assumptions!$B$4*Assumptions!$B$7 | C8: =Assumptions!$B$7*((Assumptions!$B$6*Assumptions!$B$5)*((Assumptions!$B$6*Assumptions!$B$5)+1)/2)*((C$4)^2-($A8)^2)-(Assumptions!$B$7-1)*Assumptions!$B$10-(Assumptions!$B$11+Assumptions!$B$12)*Assumptions!$B$7+Assumptions!$B$7*Assumptions!$B$13+Assumptions!$B$9/10000*Assumptions!$B$8*Assumptions!$B$4*Assumptions!$B$7 | D8: =Assumptions!$B$7*((Assumptions!$B$6*Assumptions!$B$5)*((Assumptions!$B$6*Assumptions!$B$5)+1)/2)*((D$4)^2-($A8)^2)-(Assumptions!$B$7-1)*Assumptions!$B$10-(Assumptions!$B$11+Assumptions!$B$12)*Assumptions!$B$7+Assumptions!$B$7*Assumptions!$B$13+Assumptions!$B$9/10000*Assumptions!$B$8*Assumptions!$B$4*Assumptions!$B$7 | E8: =Assumptions!$B$7*((Assumptions!$B$6*Assumptions!$B$5)*((Assumptions!$B$6*Assumptions!$B$5)+1)/2)*((E$4)^2-($A8)^2)-(Assumptions!$B$7-1)*Assumptions!$B$10-(Assumptions!$B$11+Assumptions!$B$12)*Assumptions!$B$7+Assumptions!$B$7*Assumptions!$B$13+Assumptions!$B$9/10000*Assumptions!$B$8*Assumptions!$B$4*Assumptions!$B$7 | F8: =Assumptions!$B$7*((Assumptions!$B$6*Assumptions!$B$5)*((Assumptions!$B$6*Assumptions!$B$5)+1)/2)*((F$4)^2-($A8)^2)-(Assumptions!$B$7-1)*Assumptions!$B$10-(Assumptions!$B$11+Assumptions!$B$12)*Assumptions!$B$7+Assumptions!$B$7*Assumptions!$B$13+Assumptions!$B$9/10000*Assumptions!$B$8*Assumptions!$B$4*Assumptions!$B$7
A9: =Assumptions!F$17 | B9: =Assumptions!$B$7*((Assumptions!$B$6*Assumptions!$B$5)*((Assumptions!$B$6*Assumptions!$B$5)+1)/2)*((B$4)^2-($A9)^2)-(Assumptions!$B$7-1)*Assumptions!$B$10-(Assumptions!$B$11+Assumptions!$B$12)*Assumptions!$B$7+Assumptions!$B$7*Assumptions!$B$13+Assumptions!$B$9/10000*Assumptions!$B$8*Assumptions!$B$4*Assumptions!$B$7 | C9: =Assumptions!$B$7*((Assumptions!$B$6*Assumptions!$B$5)*((Assumptions!$B$6*Assumptions!$B$5)+1)/2)*((C$4)^2-($A9)^2)-(Assumptions!$B$7-1)*Assumptions!$B$10-(Assumptions!$B$11+Assumptions!$B$12)*Assumptions!$B$7+Assumptions!$B$7*Assumptions!$B$13+Assumptions!$B$9/10000*Assumptions!$B$8*Assumptions!$B$4*Assumptions!$B$7 | D9: =Assumptions!$B$7*((Assumptions!$B$6*Assumptions!$B$5)*((Assumptions!$B$6*Assumptions!$B$5)+1)/2)*((D$4)^2-($A9)^2)-(Assumptions!$B$7-1)*Assumptions!$B$10-(Assumptions!$B$11+Assumptions!$B$12)*Assumptions!$B$7+Assumptions!$B$7*Assumptions!$B$13+Assumptions!$B$9/10000*Assumptions!$B$8*Assumptions!$B$4*Assumptions!$B$7 | E9: =Assumptions!$B$7*((Assumptions!$B$6*Assumptions!$B$5)*((Assumptions!$B$6*Assumptions!$B$5)+1)/2)*((E$4)^2-($A9)^2)-(Assumptions!$B$7-1)*Assumptions!$B$10-(Assumptions!$B$11+Assumptions!$B$12)*Assumptions!$B$7+Assumptions!$B$7*Assumptions!$B$13+Assumptions!$B$9/10000*Assumptions!$B$8*Assumptions!$B$4*Assumptions!$B$7 | F9: =Assumptions!$B$7*((Assumptions!$B$6*Assumptions!$B$5)*((Assumptions!$B$6*Assumptions!$B$5)+1)/2)*((F$4)^2-($A9)^2)-(Assumptions!$B$7-1)*Assumptions!$B$10-(Assumptions!$B$11+Assumptions!$B$12)*Assumptions!$B$7+Assumptions!$B$7*Assumptions!$B$13+Assumptions!$B$9/10000*Assumptions!$B$8*Assumptions!$B$4*Assumptions!$B$7
A12: RESTAKED — + HLP margin.
A13: RV \ sigma_cal | B13: =Assumptions!B$18 | C13: =Assumptions!C$18 | D13: =Assumptions!D$18 | E13: =Assumptions!E$18 | F13: =Assumptions!F$18
A14: =Assumptions!B$17 | B14: =(Assumptions!$B$7*((Assumptions!$B$6*Assumptions!$B$5)*((Assumptions!$B$6*Assumptions!$B$5)+1)/2)*((B$13)^2-($A14)^2)-(Assumptions!$B$7-1)*Assumptions!$B$10-(Assumptions!$B$11+Assumptions!$B$12)*Assumptions!$B$7+Assumptions!$B$7*Assumptions!$B$13+Assumptions!$B$9/10000*Assumptions!$B$8*Assumptions!$B$4*Assumptions!$B$7)+Assumptions!$B$14*(1-Assumptions!$B$15*$A14) | C14: =(Assumptions!$B$7*((Assumptions!$B$6*Assumptions!$B$5)*((Assumptions!$B$6*Assumptions!$B$5)+1)/2)*((C$13)^2-($A14)^2)-(Assumptions!$B$7-1)*Assumptions!$B$10-(Assumptions!$B$11+Assumptions!$B$12)*Assumptions!$B$7+Assumptions!$B$7*Assumptions!$B$13+Assumptions!$B$9/10000*Assumptions!$B$8*Assumptions!$B$4*Assumptions!$B$7)+Assumptions!$B$14*(1-Assumptions!$B$15*$A14) | D14: =(Assumptions!$B$7*((Assumptions!$B$6*Assumptions!$B$5)*((Assumptions!$B$6*Assumptions!$B$5)+1)/2)*((D$13)^2-($A14)^2)-(Assumptions!$B$7-1)*Assumptions!$B$10-(Assumptions!$B$11+Assumptions!$B$12)*Assumptions!$B$7+Assumptions!$B$7*Assumptions!$B$13+Assumptions!$B$9/10000*Assumptions!$B$8*Assumptions!$B$4*Assumptions!$B$7)+Assumptions!$B$14*(1-Assumptions!$B$15*$A14) | E14: =(Assumptions!$B$7*((Assumptions!$B$6*Assumptions!$B$5)*((Assumptions!$B$6*Assumptions!$B$5)+1)/2)*((E$13)^2-($A14)^2)-(Assumptions!$B$7-1)*Assumptions!$B$10-(Assumptions!$B$11+Assumptions!$B$12)*Assumptions!$B$7+Assumptions!$B$7*Assumptions!$B$13+Assumptions!$B$9/10000*Assumptions!$B$8*Assumptions!$B$4*Assumptions!$B$7)+Assumptions!$B$14*(1-Assumptions!$B$15*$A14) | F14: =(Assumptions!$B$7*((Assumptions!$B$6*Assumptions!$B$5)*((Assumptions!$B$6*Assumptions!$B$5)+1)/2)*((F$13)^2-($A14)^2)-(Assumptions!$B$7-1)*Assumptions!$B$10-(Assumptions!$B$11+Assumptions!$B$12)*Assumptions!$B$7+Assumptions!$B$7*Assumptions!$B$13+Assumptions!$B$9/10000*Assumptions!$B$8*Assumptions!$B$4*Assumptions!$B$7)+Assumptions!$B$14*(1-Assumptions!$B$15*$A14)
A15: =Assumptions!C$17 | B15: =(Assumptions!$B$7*((Assumptions!$B$6*Assumptions!$B$5)*((Assumptions!$B$6*Assumptions!$B$5)+1)/2)*((B$13)^2-($A15)^2)-(Assumptions!$B$7-1)*Assumptions!$B$10-(Assumptions!$B$11+Assumptions!$B$12)*Assumptions!$B$7+Assumptions!$B$7*Assumptions!$B$13+Assumptions!$B$9/10000*Assumptions!$B$8*Assumptions!$B$4*Assumptions!$B$7)+Assumptions!$B$14*(1-Assumptions!$B$15*$A15) | C15: =(Assumptions!$B$7*((Assumptions!$B$6*Assumptions!$B$5)*((Assumptions!$B$6*Assumptions!$B$5)+1)/2)*((C$13)^2-($A15)^2)-(Assumptions!$B$7-1)*Assumptions!$B$10-(Assumptions!$B$11+Assumptions!$B$12)*Assumptions!$B$7+Assumptions!$B$7*Assumptions!$B$13+Assumptions!$B$9/10000*Assumptions!$B$8*Assumptions!$B$4*Assumptions!$B$7)+Assumptions!$B$14*(1-Assumptions!$B$15*$A15) | D15: =(Assumptions!$B$7*((Assumptions!$B$6*Assumptions!$B$5)*((Assumptions!$B$6*Assumptions!$B$5)+1)/2)*((D$13)^2-($A15)^2)-(Assumptions!$B$7-1)*Assumptions!$B$10-(Assumptions!$B$11+Assumptions!$B$12)*Assumptions!$B$7+Assumptions!$B$7*Assumptions!$B$13+Assumptions!$B$9/10000*Assumptions!$B$8*Assumptions!$B$4*Assumptions!$B$7)+Assumptions!$B$14*(1-Assumptions!$B$15*$A15) | E15: =(Assumptions!$B$7*((Assumptions!$B$6*Assumptions!$B$5)*((Assumptions!$B$6*Assumptions!$B$5)+1)/2)*((E$13)^2-($A15)^2)-(Assumptions!$B$7-1)*Assumptions!$B$10-(Assumptions!$B$11+Assumptions!$B$12)*Assumptions!$B$7+Assumptions!$B$7*Assumptions!$B$13+Assumptions!$B$9/10000*Assumptions!$B$8*Assumptions!$B$4*Assumptions!$B$7)+Assumptions!$B$14*(1-Assumptions!$B$15*$A15) | F15: =(Assumptions!$B$7*((Assumptions!$B$6*Assumptions!$B$5)*((Assumptions!$B$6*Assumptions!$B$5)+1)/2)*((F$13)^2-($A15)^2)-(Assumptions!$B$7-1)*Assumptions!$B$10-(Assumptions!$B$11+Assumptions!$B$12)*Assumptions!$B$7+Assumptions!$B$7*Assumptions!$B$13+Assumptions!$B$9/10000*Assumptions!$B$8*Assumptions!$B$4*Assumptions!$B$7)+Assumptions!$B$14*(1-Assumptions!$B$15*$A15)
A16: =Assumptions!D$17 | B16: =(Assumptions!$B$7*((Assumptions!$B$6*Assumptions!$B$5)*((Assumptions!$B$6*Assumptions!$B$5)+1)/2)*((B$13)^2-($A16)^2)-(Assumptions!$B$7-1)*Assumptions!$B$10-(Assumptions!$B$11+Assumptions!$B$12)*Assumptions!$B$7+Assumptions!$B$7*Assumptions!$B$13+Assumptions!$B$9/10000*Assumptions!$B$8*Assumptions!$B$4*Assumptions!$B$7)+Assumptions!$B$14*(1-Assumptions!$B$15*$A16) | C16: =(Assumptions!$B$7*((Assumptions!$B$6*Assumptions!$B$5)*((Assumptions!$B$6*Assumptions!$B$5)+1)/2)*((C$13)^2-($A16)^2)-(Assumptions!$B$7-1)*Assumptions!$B$10-(Assumptions!$B$11+Assumptions!$B$12)*Assumptions!$B$7+Assumptions!$B$7*Assumptions!$B$13+Assumptions!$B$9/10000*Assumptions!$B$8*Assumptions!$B$4*Assumptions!$B$7)+Assumptions!$B$14*(1-Assumptions!$B$15*$A16) | D16: =(Assumptions!$B$7*((Assumptions!$B$6*Assumptions!$B$5)*((Assumptions!$B$6*Assumptions!$B$5)+1)/2)*((D$13)^2-($A16)^2)-(Assumptions!$B$7-1)*Assumptions!$B$10-(Assumptions!$B$11+Assumptions!$B$12)*Assumptions!$B$7+Assumptions!$B$7*Assumptions!$B$13+Assumptions!$B$9/10000*Assumptions!$B$8*Assumptions!$B$4*Assumptions!$B$7)+Assumptions!$B$14*(1-Assumptions!$B$15*$A16) | E16: =(Assumptions!$B$7*((Assumptions!$B$6*Assumptions!$B$5)*((Assumptions!$B$6*Assumptions!$B$5)+1)/2)*((E$13)^2-($A16)^2)-(Assumptions!$B$7-1)*Assumptions!$B$10-(Assumptions!$B$11+Assumptions!$B$12)*Assumptions!$B$7+Assumptions!$B$7*Assumptions!$B$13+Assumptions!$B$9/10000*Assumptions!$B$8*Assumptions!$B$4*Assumptions!$B$7)+Assumptions!$B$14*(1-Assumptions!$B$15*$A16) | F16: =(Assumptions!$B$7*((Assumptions!$B$6*Assumptions!$B$5)*((Assumptions!$B$6*Assumptions!$B$5)+1)/2)*((F$13)^2-($A16)^2)-(Assumptions!$B$7-1)*Assumptions!$B$10-(Assumptions!$B$11+Assumptions!$B$12)*Assumptions!$B$7+Assumptions!$B$7*Assumptions!$B$13+Assumptions!$B$9/10000*Assumptions!$B$8*Assumptions!$B$4*Assumptions!$B$7)+Assumptions!$B$14*(1-Assumptions!$B$15*$A16)
A17: =Assumptions!E$17 | B17: =(Assumptions!$B$7*((Assumptions!$B$6*Assumptions!$B$5)*((Assumptions!$B$6*Assumptions!$B$5)+1)/2)*((B$13)^2-($A17)^2)-(Assumptions!$B$7-1)*Assumptions!$B$10-(Assumptions!$B$11+Assumptions!$B$12)*Assumptions!$B$7+Assumptions!$B$7*Assumptions!$B$13+Assumptions!$B$9/10000*Assumptions!$B$8*Assumptions!$B$4*Assumptions!$B$7)+Assumptions!$B$14*(1-Assumptions!$B$15*$A17) | C17: =(Assumptions!$B$7*((Assumptions!$B$6*Assumptions!$B$5)*((Assumptions!$B$6*Assumptions!$B$5)+1)/2)*((C$13)^2-($A17)^2)-(Assumptions!$B$7-1)*Assumptions!$B$10-(Assumptions!$B$11+Assumptions!$B$12)*Assumptions!$B$7+Assumptions!$B$7*Assumptions!$B$13+Assumptions!$B$9/10000*Assumptions!$B$8*Assumptions!$B$4*Assumptions!$B$7)+Assumptions!$B$14*(1-Assumptions!$B$15*$A17) | D17: =(Assumptions!$B$7*((Assumptions!$B$6*Assumptions!$B$5)*((Assumptions!$B$6*Assumptions!$B$5)+1)/2)*((D$13)^2-($A17)^2)-(Assumptions!$B$7-1)*Assumptions!$B$10-(Assumptions!$B$11+Assumptions!$B$12)*Assumptions!$B$7+Assumptions!$B$7*Assumptions!$B$13+Assumptions!$B$9/10000*Assumptions!$B$8*Assumptions!$B$4*Assumptions!$B$7)+Assumptions!$B$14*(1-Assumptions!$B$15*$A17) | E17: =(Assumptions!$B$7*((Assumptions!$B$6*Assumptions!$B$5)*((Assumptions!$B$6*Assumptions!$B$5)+1)/2)*((E$13)^2-($A17)^2)-(Assumptions!$B$7-1)*Assumptions!$B$10-(Assumptions!$B$11+Assumptions!$B$12)*Assumptions!$B$7+Assumptions!$B$7*Assumptions!$B$13+Assumptions!$B$9/10000*Assumptions!$B$8*Assumptions!$B$4*Assumptions!$B$7)+Assumptions!$B$14*(1-Assumptions!$B$15*$A17) | F17: =(Assumptions!$B$7*((Assumptions!$B$6*Assumptions!$B$5)*((Assumptions!$B$6*Assumptions!$B$5)+1)/2)*((F$13)^2-($A17)^2)-(Assumptions!$B$7-1)*Assumptions!$B$10-(Assumptions!$B$11+Assumptions!$B$12)*Assumptions!$B$7+Assumptions!$B$7*Assumptions!$B$13+Assumptions!$B$9/10000*Assumptions!$B$8*Assumptions!$B$4*Assumptions!$B$7)+Assumptions!$B$14*(1-Assumptions!$B$15*$A17)
A18: =Assumptions!F$17 | B18: =(Assumptions!$B$7*((Assumptions!$B$6*Assumptions!$B$5)*((Assumptions!$B$6*Assumptions!$B$5)+1)/2)*((B$13)^2-($A18)^2)-(Assumptions!$B$7-1)*Assumptions!$B$10-(Assumptions!$B$11+Assumptions!$B$12)*Assumptions!$B$7+Assumptions!$B$7*Assumptions!$B$13+Assumptions!$B$9/10000*Assumptions!$B$8*Assumptions!$B$4*Assumptions!$B$7)+Assumptions!$B$14*(1-Assumptions!$B$15*$A18) | C18: =(Assumptions!$B$7*((Assumptions!$B$6*Assumptions!$B$5)*((Assumptions!$B$6*Assumptions!$B$5)+1)/2)*((C$13)^2-($A18)^2)-(Assumptions!$B$7-1)*Assumptions!$B$10-(Assumptions!$B$11+Assumptions!$B$12)*Assumptions!$B$7+Assumptions!$B$7*Assumptions!$B$13+Assumptions!$B$9/10000*Assumptions!$B$8*Assumptions!$B$4*Assumptions!$B$7)+Assumptions!$B$14*(1-Assumptions!$B$15*$A18) | D18: =(Assumptions!$B$7*((Assumptions!$B$6*Assumptions!$B$5)*((Assumptions!$B$6*Assumptions!$B$5)+1)/2)*((D$13)^2-($A18)^2)-(Assumptions!$B$7-1)*Assumptions!$B$10-(Assumptions!$B$11+Assumptions!$B$12)*Assumptions!$B$7+Assumptions!$B$7*Assumptions!$B$13+Assumptions!$B$9/10000*Assumptions!$B$8*Assumptions!$B$4*Assumptions!$B$7)+Assumptions!$B$14*(1-Assumptions!$B$15*$A18) | E18: =(Assumptions!$B$7*((Assumptions!$B$6*Assumptions!$B$5)*((Assumptions!$B$6*Assumptions!$B$5)+1)/2)*((E$13)^2-($A18)^2)-(Assumptions!$B$7-1)*Assumptions!$B$10-(Assumptions!$B$11+Assumptions!$B$12)*Assumptions!$B$7+Assumptions!$B$7*Assumptions!$B$13+Assumptions!$B$9/10000*Assumptions!$B$8*Assumptions!$B$4*Assumptions!$B$7)+Assumptions!$B$14*(1-Assumptions!$B$15*$A18) | F18: =(Assumptions!$B$7*((Assumptions!$B$6*Assumptions!$B$5)*((Assumptions!$B$6*Assumptions!$B$5)+1)/2)*((F$13)^2-($A18)^2)-(Assumptions!$B$7-1)*Assumptions!$B$10-(Assumptions!$B$11+Assumptions!$B$12)*Assumptions!$B$7+Assumptions!$B$7*Assumptions!$B$13+Assumptions!$B$9/10000*Assumptions!$B$8*Assumptions!$B$4*Assumptions!$B$7)+Assumptions!$B$14*(1-Assumptions!$B$15*$A18)
A21: Green where calibration vol > realized vol (calmer than priced); red in spikes / poor calibration. m amplifies both.

Sheet Scenario_calc
A1: SINGLE-SCENARIO BREAKDOWN (edit yellow: RV, sigma_cal)
A3: realized_vol RV | B3: 0.6
A4: sigma_cal (calibration vol) | B4: 0.7
A6: G = (m*gamma)(m*gamma+1)/2 | B6: =((Assumptions!$B$6*Assumptions!$B$5)*((Assumptions!$B$6*Assumptions!$B$5)+1)/2)
A7: Carry income (+, at sigma_cal) | B7: =Assumptions!$B$7*((Assumptions!$B$6*Assumptions!$B$5)*((Assumptions!$B$6*Assumptions!$B$5)+1)/2)*$B$4^2
A8: Vol cost / gamma bleed (LVR-equiv, RISK 1) | B8: =-Assumptions!$B$7*((Assumptions!$B$6*Assumptions!$B$5)*((Assumptions!$B$6*Assumptions!$B$5)+1)/2)*$B$3^2
A9: options_net (carry + vol cost) | B9: =Assumptions!$B$7*((Assumptions!$B$6*Assumptions!$B$5)*((Assumptions!$B$6*Assumptions!$B$5)+1)/2)*($B$4^2-$B$3^2)
A10: Fee income | B10: =Assumptions!$B$9/10000*Assumptions!$B$8*Assumptions!$B$4*Assumptions!$B$7
A11: Financing | B11: =-(Assumptions!$B$7-1)*Assumptions!$B$10
A12: Hedge+exec+order-mgmt cost | B12: =-(Assumptions!$B$11+Assumptions!$B$12)*Assumptions!$B$7+Assumptions!$B$7*Assumptions!$B$13
A13: BASE net (dollar margin) | B13: =B8+B9+B10+B11
A14: HLP layer | B14: =Assumptions!$B$14*(1-Assumptions!$B$15*$B$3)
A15: RESTAKED net (HLP margin) | B15: =B12+B13
