Workbook

Sheet READ_ME
A1: Temporal LP economics — editable model (v2.1, +LP leverage +delta-hedge) — BRAINSTORM / non-core
A2: AUDITED (opus): arithmetic clean. Defaults are CONSERVATIVE (protection_factor=0) so the green grid is NOT an optimism-on headline.
A4: DELTA-HEDGED LP — how this model treats it:
A5: The bands are delta-hedged on Hyperliquid (see the hedging schedule). This model already represents a delta-hedged LP:
A6: - there is NO price-direction P&L term (hedging removes direction), and
A7: - LVR = sigma^2/8 IS, by definition, the loss that REMAINS after a perfect delta hedge (hedging removes direction, not LVR).
A8: Hedge assumed ~FEE-NEUTRAL (maker rebates approx taker fees) -> hedge_fee_cost default 0. Edit it if the hedge has a net cost.
A9: Hedge-leg FUNDING (funding earned/paid on the HL hedge positions themselves) is a SEPARATE channel: hedge_funding_APR (can be +/-).
A10: CAVEAT (unproven): that Temporal's band-hedge schedule achieves clean delta-neutrality with LVR as the exact residual, and the
A11: tracking error / discrete-rebalance slippage, are modeling assumptions — not validated here.
A13: MODEL (per $ equity, annualized):
A14: Temporal_net = fee_bps/10000*turnover*days + funding_APR - (sigma^2/8)*(1-protection) - drain*turnover - hedge_fee_cost + hedge_funding_APR
... A21: Reduced-form sketch, NOT a backtest. Lives in sims/ (non-core).

Sheet Assumptions
A1: EDITABLE ASSUMPTIONS (edit the yellow cells; everything recomputes)
A3: Assumption | B3: Value | C3: Disclosure / note
A4: days_per_year | B4: 365 | C4: trading days/year
A5: fee_bps | B5: 5 | C5: taker fee, bps of notional traded. 0 if no fee (TBD).
A6: funding_APR | B6: 0.03 | C6: NET funding income/yr to LP (PLACEHOLDER for update-2 formula). CAN BE NEGATIVE (LP on paying side). The hypothesized edge.
A7: protection_factor | B7: 0 | C7: WARP-only LVR reduction (0..1). Default 0 = none (conservative). Do NOT also attribute the funding tether here (=funding_APR) -> double-count. Unproven.
A8: drain_coeff | B8: 0.005 | C8: round-trip drain APR per 1.0 daily turnover.
A9: hedge_fee_cost | B9: 0 | C9: net fee cost of the delta hedge on HL, APR. ~0 under the fee-neutral assumption (maker rebates approx taker fees).
A10: hedge_funding_APR | B10: 0 | C10: net funding earned(+)/paid(-) on the HL hedge legs themselves. Separate from LVR; either sign.
A11: HLP_base_APR | B11: 0.1 | C11: yield on HLP margin (external). NOT levered.
A12: HLP_tail_haircut | B12: 0 | C12: 0=pure additive; >0 shaves HLP yield as vol rises (crash co-movement).
A13: LP_leverage | B13: 2 | C13: leverage on the TEMPORAL position only (equity xL). NOT applied to HLP.
A14: borrow_APR | B14: 0.06 | C14: cost of the borrowed (L-1) leg.
A16: Grid axes (editable):
A17: daily_turnover -> | B17: 0.25 | C17: 0.5 | D17: 1 | E17: 2 | F17: 5
A18: sigma (annualized) -> | B18: 0.2 | C18: 0.4 | D18: 0.6 | E18: 0.9 | F18: 1.2
A20: Legend: yellow = editable input.

Sheet Regime_Grid
A1: REGIME GRID — net LP yield (APR). green = LP profits / red = LP loses. Inputs on 'Assumptions'.
A3: LEVERED LP (dollar margin) — net yield APR.
A4: sigma \ turnover(/day) | B4: =Assumptions!B$17 | C4: =Assumptions!C$17 | D4: =Assumptions!D$17 | E4: =Assumptions!E$17 | F4: =Assumptions!F$17
A5: =Assumptions!B$18 | B5: =(Assumptions!$B$13*(Assumptions!$B$5/10000*B$4*Assumptions!$B$4+Assumptions!$B$6-(($A5^2)/8)*(1-Assumptions!$B$7)-Assumptions!$B$8*B$4-Assumptions!$B$9+Assumptions!$B$10)-(Assumptions!$B$13-1)*Assumptions!$B$14) | C5: =(Assumptions!$B$13*(Assumptions!$B$5/10000*C$4*Assumptions!$B$4+Assumptions!$B$6-(($A5^2)/8)*(1-Assumptions!$B$7)-Assumptions!$B$8*C$4-Assumptions!$B$9+Assumptions!$B$10)-(Assumptions!$B$13-1)*Assumptions!$B$14) | D5: =(Assumptions!$B$13*(Assumptions!$B$5/10000*D$4*Assumptions!$B$4+Assumptions!$B$6-(($A5^2)/8)*(1-Assumptions!$B$7)-Assumptions!$B$8*D$4-Assumptions!$B$9+Assumptions!$B$10)-(Assumptions!$B$13-1)*Assumptions!$B$14) | E5: =(Assumptions!$B$13*(Assumptions!$B$5/10000*E$4*Assumptions!$B$4+Assumptions!$B$6-(($A5^2)/8)*(1-Assumptions!$B$7)-Assumptions!$B$8*E$4-Assumptions!$B$9+Assumptions!$B$10)-(Assumptions!$B$13-1)*Assumptions!$B$14) | F5: =(Assumptions!$B$13*(Assumptions!$B$5/10000*F$4*Assumptions!$B$4+Assumptions!$B$6-(($A5^2)/8)*(1-Assumptions!$B$7)-Assumptions!$B$8*F$4-Assumptions!$B$9+Assumptions!$B$10)-(Assumptions!$B$13-1)*Assumptions!$B$14)
A6: =Assumptions!C$18 | B6: =(Assumptions!$B$13*(Assumptions!$B$5/10000*B$4*Assumptions!$B$4+Assumptions!$B$6-(($A6^2)/8)*(1-Assumptions!$B$7)-Assumptions!$B$8*B$4-Assumptions!$B$9+Assumptions!$B$10)-(Assumptions!$B$13-1)*Assumptions!$B$14) | C6: =(Assumptions!$B$13*(Assumptions!$B$5/10000*C$4*Assumptions!$B$4+Assumptions!$B$6-(($A6^2)/8)*(1-Assumptions!$B$7)-Assumptions!$B$8*C$4-Assumptions!$B$9+Assumptions!$B$10)-(Assumptions!$B$13-1)*Assumptions!$B$14) | D6: =(Assumptions!$B$13*(Assumptions!$B$5/10000*D$4*Assumptions!$B$4+Assumptions!$B$6-(($A6^2)/8)*(1-Assumptions!$B$7)-Assumptions!$B$8*D$4-Assumptions!$B$9+Assumptions!$B$10)-(Assumptions!$B$13-1)*Assumptions!$B$14) | E6: =(Assumptions!$B$13*(Assumptions!$B$5/10000*E$4*Assumptions!$B$4+Assumptions!$B$6-(($A6^2)/8)*(1-Assumptions!$B$7)-Assumptions!$B$8*E$4-Assumptions!$B$9+Assumptions!$B$10)-(Assumptions!$B$13-1)*Assumptions!$B$14) | F6: =(Assumptions!$B$13*(Assumptions!$B$5/10000*F$4*Assumptions!$B$4+Assumptions!$B$6-(($A6^2)/8)*(1-Assumptions!$B$7)-Assumptions!$B$8*F$4-Assumptions!$B$9+Assumptions!$B$10)-(Assumptions!$B$13-1)*Assumptions!$B$14)
A7: =Assumptions!D$18 | B7: =(Assumptions!$B$13*(Assumptions!$B$5/10000*B$4*Assumptions!$B$4+Assumptions!$B$6-(($A7^2)/8)*(1-Assumptions!$B$7)-Assumptions!$B$8*B$4-Assumptions!$B$9+Assumptions!$B$10)-(Assumptions!$B$13-1)*Assumptions!$B$14) | C7: =(Assumptions!$B$13*(Assumptions!$B$5/10000*C$4*Assumptions!$B$4+Assumptions!$B$6-(($A7^2)/8)*(1-Assumptions!$B$7)-Assumptions!$B$8*C$4-Assumptions!$B$9+Assumptions!$B$10)-(Assumptions!$B$13-1)*Assumptions!$B$14) | D7: =(Assumptions!$B$13*(Assumptions!$B$5/10000*D$4*Assumptions!$B$4+Assumptions!$B$6-(($A7^2)/8)*(1-Assumptions!$B$7)-Assumptions!$B$8*D$4-Assumptions!$B$9+Assumptions!$B$10)-(Assumptions!$B$13-1)*Assumptions!$B$14) | E7: =(Assumptions!$B$13*(Assumptions!$B$5/10000*E$4*Assumptions!$B$4+Assumptions!$B$6-(($A7^2)/8)*(1-Assumptions!$B$7)-Assumptions!$B$8*E$4-Assumptions!$B$9+Assumptions!$B$10)-(Assumptions!$B$13-1)*Assumptions!$B$14) | F7: =(Assumptions!$B$13*(Assumptions!$B$5/10000*F$4*Assumptions!$B$4+Assumptions!$B$6-(($A7^2)/8)*(1-Assumptions!$B$7)-Assumptions!$B$8*F$4-Assumptions!$B$9+Assumptions!$B$10)-(Assumptions!$B$13-1)*Assumptions!$B$14)
A8: =Assumptions!E$18 | B8: =(Assumptions!$B$13*(Assumptions!$B$5/10000*B$4*Assumptions!$B$4+Assumptions!$B$6-(($A8^2)/8)*(1-Assumptions!$B$7)-Assumptions!$B$8*B$4-Assumptions!$B$9+Assumptions!$B$10)-(Assumptions!$B$13-1)*Assumptions!$B$14) | C8: =(Assumptions!$B$13*(Assumptions!$B$5/10000*C$4*Assumptions!$B$4+Assumptions!$B$6-(($A8^2)/8)*(1-Assumptions!$B$7)-Assumptions!$B$8*C$4-Assumptions!$B$9+Assumptions!$B$10)-(Assumptions!$B$13-1)*Assumptions!$B$14) | D8: =(Assumptions!$B$13*(Assumptions!$B$5/10000*D$4*Assumptions!$B$4+Assumptions!$B$6-(($A8^2)/8)*(1-Assumptions!$B$7)-Assumptions!$B$8*D$4-Assumptions!$B$9+Assumptions!$B$10)-(Assumptions!$B$13-1)*Assumptions!$B$14) | E8: =(Assumptions!$B$13*(Assumptions!$B$5/10000*E$4*Assumptions!$B$4+Assumptions!$B$6-(($A8^2)/8)*(1-Assumptions!$B$7)-Assumptions!$B$8*E$4-Assumptions!$B$9+Assumptions!$B$10)-(Assumptions!$B$13-1)*Assumptions!$B$14) | F8: =(Assumptions!$B$13*(Assumptions!$B$5/10000*F$4*Assumptions!$B$4+Assumptions!$B$6-(($A8^2)/8)*(1-Assumptions!$B$7)-Assumptions!$B$8*F$4-Assumptions!$B$9+Assumptions!$B$10)-(Assumptions!$B$13-1)*Assumptions!$B$14)
A9: =Assumptions!F$18 | B9: =(Assumptions!$B$13*(Assumptions!$B$5/10000*B$4*Assumptions!$B$4+Assumptions!$B$6-(($A9^2)/8)*(1-Assumptions!$B$7)-Assumptions!$B$8*B$4-Assumptions!$B$9+Assumptions!$B$10)-(Assumptions!$B$13-1)*Assumptions!$B$14) | C9: =(Assumptions!$B$13*(Assumptions!$B$5/10000*C$4*Assumptions!$B$4+Assumptions!$B$6-(($A9^2)/8)*(1-Assumptions!$B$7)-Assumptions!$B$8*C$4-Assumptions!$B$9+Assumptions!$B$10)-(Assumptions!$B$13-1)*Assumptions!$B$14) | D9: =(Assumptions!$B$13*(Assumptions!$B$5/10000*D$4*Assumptions!$B$4+Assumptions!$B$6-(($A9^2)/8)*(1-Assumptions!$B$7)-Assumptions!$B$8*D$4-Assumptions!$B$9+Assumptions!$B$10)-(Assumptions!$B$13-1)*Assumptions!$B$14) | E9: =(Assumptions!$B$13*(Assumptions!$B$5/10000*E$4*Assumptions!$B$4+Assumptions!$B$6-(($A9^2)/8)*(1-Assumptions!$B$7)-Assumptions!$B$8*E$4-Assumptions!$B$9+Assumptions!$B$10)-(Assumptions!$B$13-1)*Assumptions!$B$14) | F9: =(Assumptions!$B$13*(Assumptions!$B$5/10000*F$4*Assumptions!$B$4+Assumptions!$B$6-(($A9^2)/8)*(1-Assumptions!$B$7)-Assumptions!$B$8*F$4-Assumptions!$B$9+Assumptions!$B$10)-(Assumptions!$B$13-1)*Assumptions!$B$14)
A12: LEVERED + RESTAKED (HLP margin) — net yield APR.
A13: sigma \ turnover(/day) | B13: =Assumptions!B$17 | C13: =Assumptions!C$17 | D13: =Assumptions!D$17 | E13: =Assumptions!E$17 | F13: =Assumptions!F$17
A14: =Assumptions!B$18 | B14: =(Assumptions!$B$13*(Assumptions!$B$5/10000*B$13*Assumptions!$B$4+Assumptions!$B$6-(($A14^2)/8)*(1-Assumptions!$B$7)-Assumptions!$B$8*B$13-Assumptions!$B$9+Assumptions!$B$10)-(Assumptions!$B$13-1)*Assumptions!$B$14)+Assumptions!$B$11*(1-Assumptions!$B$12*$A14) | C14: =(Assumptions!$B$13*(Assumptions!$B$5/10000*C$13*Assumptions!$B$4+Assumptions!$B$6-(($A14^2)/8)*(1-Assumptions!$B$7)-Assumptions!$B$8*C$13-Assumptions!$B$9+Assumptions!$B$10)-(Assumptions!$B$13-1)*Assumptions!$B$14)+Assumptions!$B$11*(1-Assumptions!$B$12*$A14) | D14: =(Assumptions!$B$13*(Assumptions!$B$5/10000*D$13*Assumptions!$B$4+Assumptions!$B$6-(($A14^2)/8)*(1-Assumptions!$B$7)-Assumptions!$B$8*D$13-Assumptions!$B$9+Assumptions!$B$10)-(Assumptions!$B$13-1)*Assumptions!$B$14)+Assumptions!$B$11*(1-Assumptions!$B$12*$A14) | E14: =(Assumptions!$B$13*(Assumptions!$B$5/10000*E$13*Assumptions!$B$4+Assumptions!$B$6-(($A14^2)/8)*(1-Assumptions!$B$7)-Assumptions!$B$8*E$13-Assumptions!$B$9+Assumptions!$B$10)-(Assumptions!$B$13-1)*Assumptions!$B$14)+Assumptions!$B$11*(1-Assumptions!$B$12*$A14) | F14: =(Assumptions!$B$13*(Assumptions!$B$5/10000*F$13*Assumptions!$B$4+Assumptions!$B$6-(($A14^2)/8)*(1-Assumptions!$B$7)-Assumptions!$B$8*F$13-Assumptions!$B$9+Assumptions!$B$10)-(Assumptions!$B$13-1)*Assumptions!$B$14)+Assumptions!$B$11*(1-Assumptions!$B$12*$A14)
A15: =Assumptions!C$18 | B15: =(Assumptions!$B$13*(Assumptions!$B$5/10000*B$13*Assumptions!$B$4+Assumptions!$B$6-(($A15^2)/8)*(1-Assumptions!$B$7)-Assumptions!$B$8*B$13-Assumptions!$B$9+Assumptions!$B$10)-(Assumptions!$B$13-1)*Assumptions!$B$14)+Assumptions!$B$11*(1-Assumptions!$B$12*$A15) | C15: =(Assumptions!$B$13*(Assumptions!$B$5/10000*C$13*Assumptions!$B$4+Assumptions!$B$6-(($A15^2)/8)*(1-Assumptions!$B$7)-Assumptions!$B$8*C$13-Assumptions!$B$9+Assumptions!$B$10)-(Assumptions!$B$13-1)*Assumptions!$B$14)+Assumptions!$B$11*(1-Assumptions!$B$12*$A15) | D15: =(Assumptions!$B$13*(Assumptions!$B$5/10000*D$13*Assumptions!$B$4+Assumptions!$B$6-(($A15^2)/8)*(1-Assumptions!$B$7)-Assumptions!$B$8*D$13-Assumptions!$B$9+Assumptions!$B$10)-(Assumptions!$B$13-1)*Assumptions!$B$14)+Assumptions!$B$11*(1-Assumptions!$B$12*$A15) | E15: =(Assumptions!$B$13*(Assumptions!$B$5/10000*E$13*Assumptions!$B$4+Assumptions!$B$6-(($A15^2)/8)*(1-Assumptions!$B$7)-Assumptions!$B$8*E$13-Assumptions!$B$9+Assumptions!$B$10)-(Assumptions!$B$13-1)*Assumptions!$B$14)+Assumptions!$B$11*(1-Assumptions!$B$12*$A15) | F15: =(Assumptions!$B$13*(Assumptions!$B$5/10000*F$13*Assumptions!$B$4+Assumptions!$B$6-(($A15^2)/8)*(1-Assumptions!$B$7)-Assumptions!$B$8*F$13-Assumptions!$B$9+Assumptions!$B$10)-(Assumptions!$B$13-1)*Assumptions!$B$14)+Assumptions!$B$11*(1-Assumptions!$B$12*$A15)
A16: =Assumptions!D$18 | B16: =(Assumptions!$B$13*(Assumptions!$B$5/10000*B$13*Assumptions!$B$4+Assumptions!$B$6-(($A16^2)/8)*(1-Assumptions!$B$7)-Assumptions!$B$8*B$13-Assumptions!$B$9+Assumptions!$B$10)-(Assumptions!$B$13-1)*Assumptions!$B$14)+Assumptions!$B$11*(1-Assumptions!$B$12*$A16) | C16: =(Assumptions!$B$13*(Assumptions!$B$5/10000*C$13*Assumptions!$B$4+Assumptions!$B$6-(($A16^2)/8)*(1-Assumptions!$B$7)-Assumptions!$B$8*C$13-Assumptions!$B$9+Assumptions!$B$10)-(Assumptions!$B$13-1)*Assumptions!$B$14)+Assumptions!$B$11*(1-Assumptions!$B$12*$A16) | D16: =(Assumptions!$B$13*(Assumptions!$B$5/10000*D$13*Assumptions!$B$4+Assumptions!$B$6-(($A16^2)/8)*(1-Assumptions!$B$7)-Assumptions!$B$8*D$13-Assumptions!$B$9+Assumptions!$B$10)-(Assumptions!$B$13-1)*Assumptions!$B$14)+Assumptions!$B$11*(1-Assumptions!$B$12*$A16) | E16: =(Assumptions!$B$13*(Assumptions!$B$5/10000*E$13*Assumptions!$B$4+Assumptions!$B$6-(($A16^2)/8)*(1-Assumptions!$B$7)-Assumptions!$B$8*E$13-Assumptions!$B$9+Assumptions!$B$10)-(Assumptions!$B$13-1)*Assumptions!$B$14)+Assumptions!$B$11*(1-Assumptions!$B$12*$A16) | F16: =(Assumptions!$B$13*(Assumptions!$B$5/10000*F$13*Assumptions!$B$4+Assumptions!$B$6-(($A16^2)/8)*(1-Assumptions!$B$7)-Assumptions!$B$8*F$13-Assumptions!$B$9+Assumptions!$B$10)-(Assumptions!$B$13-1)*Assumptions!$B$14)+Assumptions!$B$11*(1-Assumptions!$B$12*$A16)
A17: =Assumptions!E$18 | B17: =(Assumptions!$B$13*(Assumptions!$B$5/10000*B$13*Assumptions!$B$4+Assumptions!$B$6-(($A17^2)/8)*(1-Assumptions!$B$7)-Assumptions!$B$8*B$13-Assumptions!$B$9+Assumptions!$B$10)-(Assumptions!$B$13-1)*Assumptions!$B$14)+Assumptions!$B$11*(1-Assumptions!$B$12*$A17) | C17: =(Assumptions!$B$13*(Assumptions!$B$5/10000*C$13*Assumptions!$B$4+Assumptions!$B$6-(($A17^2)/8)*(1-Assumptions!$B$7)-Assumptions!$B$8*C$13-Assumptions!$B$9+Assumptions!$B$10)-(Assumptions!$B$13-1)*Assumptions!$B$14)+Assumptions!$B$11*(1-Assumptions!$B$12*$A17) | D17: =(Assumptions!$B$13*(Assumptions!$B$5/10000*D$13*Assumptions!$B$4+Assumptions!$B$6-(($A17^2)/8)*(1-Assumptions!$B$7)-Assumptions!$B$8*D$13-Assumptions!$B$9+Assumptions!$B$10)-(Assumptions!$B$13-1)*Assumptions!$B$14)+Assumptions!$B$11*(1-Assumptions!$B$12*$A17) | E17: =(Assumptions!$B$13*(Assumptions!$B$5/10000*E$13*Assumptions!$B$4+Assumptions!$B$6-(($A17^2)/8)*(1-Assumptions!$B$7)-Assumptions!$B$8*E$13-Assumptions!$B$9+Assumptions!$B$10)-(Assumptions!$B$13-1)*Assumptions!$B$14)+Assumptions!$B$11*(1-Assumptions!$B$12*$A17) | F17: =(Assumptions!$B$13*(Assumptions!$B$5/10000*F$13*Assumptions!$B$4+Assumptions!$B$6-(($A17^2)/8)*(1-Assumptions!$B$7)-Assumptions!$B$8*F$13-Assumptions!$B$9+Assumptions!$B$10)-(Assumptions!$B$13-1)*Assumptions!$B$14)+Assumptions!$B$11*(1-Assumptions!$B$12*$A17)
A18: =Assumptions!F$18 | B18: =(Assumptions!$B$13*(Assumptions!$B$5/10000*B$13*Assumptions!$B$4+Assumptions!$B$6-(($A18^2)/8)*(1-Assumptions!$B$7)-Assumptions!$B$8*B$13-Assumptions!$B$9+Assumptions!$B$10)-(Assumptions!$B$13-1)*Assumptions!$B$14)+Assumptions!$B$11*(1-Assumptions!$B$12*$A18) | C18: =(Assumptions!$B$13*(Assumptions!$B$5/10000*C$13*Assumptions!$B$4+Assumptions!$B$6-(($A18^2)/8)*(1-Assumptions!$B$7)-Assumptions!$B$8*C$13-Assumptions!$B$9+Assumptions!$B$10)-(Assumptions!$B$13-1)*Assumptions!$B$14)+Assumptions!$B$11*(1-Assumptions!$B$12*$A18) | D18: =(Assumptions!$B$13*(Assumptions!$B$5/10000*D$13*Assumptions!$B$4+Assumptions!$B$6-(($A18^2)/8)*(1-Assumptions!$B$7)-Assumptions!$B$8*D$13-Assumptions!$B$9+Assumptions!$B$10)-(Assumptions!$B$13-1)*Assumptions!$B$14)+Assumptions!$B$11*(1-Assumptions!$B$12*$A18) | E18: =(Assumptions!$B$13*(Assumptions!$B$5/10000*E$13*Assumptions!$B$4+Assumptions!$B$6-(($A18^2)/8)*(1-Assumptions!$B$7)-Assumptions!$B$8*E$13-Assumptions!$B$9+Assumptions!$B$10)-(Assumptions!$B$13-1)*Assumptions!$B$14)+Assumptions!$B$11*(1-Assumptions!$B$12*$A18) | F18: =(Assumptions!$B$13*(Assumptions!$B$5/10000*F$13*Assumptions!$B$4+Assumptions!$B$6-(($A18^2)/8)*(1-Assumptions!$B$7)-Assumptions!$B$8*F$13-Assumptions!$B$9+Assumptions!$B$10)-(Assumptions!$B$13-1)*Assumptions!$B$14)+Assumptions!$B$11*(1-Assumptions!$B$12*$A18)
A21: Break-even = green/red boundary = LEVERED break-even (Temporal_net vs borrow_APR), not zero-Temporal; ignores opportunity cost. Defaults conservative (protection=0); raise protection/funding for hypothesis-on.

Sheet Scenario_calc
A1: SINGLE-SCENARIO BREAKDOWN (edit the two yellow inputs)
A3: daily_turnover | B3: 1
A4: sigma (annualized) | B4: 0.6
A6: Fee income | B6: =Assumptions!$B$5/10000*$B$3*Assumptions!$B$4
A7: Funding income | B7: =Assumptions!$B$6
A8: LVR cost | B8: =-(($B$4^2)/8)*(1-Assumptions!$B$7)
A9: Round-trip drain | B9: =-Assumptions!$B$8*$B$3
A10: Hedge fee cost | B10: =-Assumptions!$B$9
A11: Hedge-leg funding | B11: =Assumptions!$B$10
A12: Temporal_net (unlevered, delta-hedged) | B12: =B6+B7+B8+B9+B10+B11
A13: Levered Temporal | B13: =Assumptions!$B$13*B12-(Assumptions!$B$13-1)*Assumptions!$B$14
A14: HLP layer (unlevered) | B14: =Assumptions!$B$11*(1-Assumptions!$B$12*$B$4)
A15: BASE levered net (dollar margin) | B15: =B13
A16: RESTAKED levered net (HLP margin) | B16: =B13+B14
