Workbook

Sheet 0_Inputs
A1: CONSOLIDATED MODEL — INPUTS (edit yellow; all sheets + checks recompute)
A3: CURVE / GLOBAL
A4: gamma | B4: 2 | C4: base exponent
A5: m | B5: 1 | C5: steepness knob
A6: g | B6: =B4*B5 | C6: =m*gamma (computed)
A7: Gfac | B7: =B6*(B6+1)/2 | C7: =g(g+1)/2 gamma factor (computed)
A8: u_seam | B8: =LN(B6/(B6+1)) | C8: =LN(g/(g+1)) dynamic seam
A9: V_atm | B9: =(1/(B6+1))*(B6/(B6+1))^B6 | C9: =(1/(g+1))(g/(g+1))^g
A10: RV | B10: 0.6 | C10: realized vol
A11: days | B11: 365
A12: S_ref | B12: 100000 | C12: reference price
A13: open_units | B13: 10 | C13: open option notional, UNITS
A14: turnover | B14: 0.3 | C14: traded/open per day
A15: margin_per_unit | B15: 100000 | C15: LAYER 3: $ per carved unit
A16: L0 | B16: 1 | C16: carved-slice scale
A17: hedge_ratio | B17: 1 | C17: 1=fully hedged
A18: hedge_cost | B18: 0.015 | C18: exec+order-mgmt, APR on hedge notional
A19: acct_lev_cap | B19: 50 | C19: ACCOUNT-level liquidation cap
A20: club_long | B20: 4000000 | C20: all LONG perps, shared wallet
A21: club_short | B21: 3000000 | C21: all SHORT perps
A22: margin_frac | B22: 0.2 | C22: equity per $ notional
A23: carve_frac | B23: 0.25 | C23: fraction carved to back options
A25: PER-LP — each posts its OWN depth + half-spread (two-curve design)
A26: LP | B26: depth (units) | C26: half-spread h | D26: equity $ | E26: uses HLP
A27: LP-C tight | B27: 3 | C27: 0.0005 | D27: 1000000 | E27: 0
A28: LP-B mid | B28: 2 | C28: 0.0015 | D28: 500000 | E28: 0
A29: LP-A wide | B29: 4 | C29: 0.003 | D29: 250000 | E29: 1
A31: STRIKE GRID u=LN(S/K) — V is ONE number (ITM via smooth-paste); Delta transports AND reads back
A32: u | B32: S/K | C32: V mid | D32: Delta | E32: regime | F32: q units
A33: -0.6 | B33: =EXP(A33) | C33: =IF(A33<'0_Inputs'!$B$8,1-EXP(A33),'0_Inputs'!$B$9*EXP(-'0_Inputs'!$B$6*A33)) | D33: =IF(A33<'0_Inputs'!$B$8,EXP(A33),'0_Inputs'!$B$6*C33) | E33: =IF(A33<'0_Inputs'!$B$8,"INTRINSIC","continuation") | F33: =D33/SUM($D$33:$D$37)*'0_Inputs'!$B$13
A34: -0.3 | B34: =EXP(A34) | C34: =IF(A34<'0_Inputs'!$B$8,1-EXP(A34),'0_Inputs'!$B$9*EXP(-'0_Inputs'!$B$6*A34)) | D34: =IF(A34<'0_Inputs'!$B$8,EXP(A34),'0_Inputs'!$B$6*C34) | E34: =IF(A34<'0_Inputs'!$B$8,"INTRINSIC","continuation") | F34: =D34/SUM($D$33:$D$37)*'0_Inputs'!$B$13
A35: 0 | B35: =EXP(A35) | C35: =IF(A35<'0_Inputs'!$B$8,1-EXP(A35),'0_Inputs'!$B$9*EXP(-'0_Inputs'!$B$6*A35)) | D35: =IF(A35<'0_Inputs'!$B$8,EXP(A35),'0_Inputs'!$B$6*C35) | E35: =IF(A35<'0_Inputs'!$B$8,"INTRINSIC","continuation") | F35: =D35/SUM($D$33:$D$37)*'0_Inputs'!$B$13
A36: 0.3 | B36: =EXP(A36) | C36: =IF(A36<'0_Inputs'!$B$8,1-EXP(A36),'0_Inputs'!$B$9*EXP(-'0_Inputs'!$B$6*A36)) | D36: =IF(A36<'0_Inputs'!$B$8,EXP(A36),'0_Inputs'!$B$6*C36) | E36: =IF(A36<'0_Inputs'!$B$8,"INTRINSIC","continuation") | F36: =D36/SUM($D$33:$D$37)*'0_Inputs'!$B$13
A37: 0.6 | B37: =EXP(A37) | C37: =IF(A37<'0_Inputs'!$B$8,1-EXP(A37),'0_Inputs'!$B$9*EXP(-'0_Inputs'!$B$6*A37)) | D37: =IF(A37<'0_Inputs'!$B$8,EXP(A37),'0_Inputs'!$B$6*C37) | E37: =IF(A37<'0_Inputs'!$B$8,"INTRINSIC","continuation") | F37: =D37/SUM($D$33:$D$37)*'0_Inputs'!$B$13

Sheet 1_Curves
A1: TWO CURVE SETS — bid / mid / ask. Mid is COMMON (no smile); LPs vary depth + half-spread
A3: u | B3: V mid | C3: h_agg (tightest) | D3: V bid | E3: V ask | F3: spread | G3: Delta
A4: ='0_Inputs'!A33 | B4: ='0_Inputs'!C33 | C4: =MIN('0_Inputs'!$C$27,'0_Inputs'!$C$28,'0_Inputs'!$C$29) | D4: =B4*(1-C4) | E4: =B4*(1+C4) | F4: =E4-D4 | G4: ='0_Inputs'!D33
A5: ='0_Inputs'!A34 | B5: ='0_Inputs'!C34 | C5: =MIN('0_Inputs'!$C$27,'0_Inputs'!$C$28,'0_Inputs'!$C$29) | D5: =B5*(1-C5) | E5: =B5*(1+C5) | F5: =E5-D5 | G5: ='0_Inputs'!D34
A6: ='0_Inputs'!A35 | B6: ='0_Inputs'!C35 | C6: =MIN('0_Inputs'!$C$27,'0_Inputs'!$C$28,'0_Inputs'!$C$29) | D6: =B6*(1-C6) | E6: =B6*(1+C6) | F6: =E6-D6 | G6: ='0_Inputs'!D35
A7: ='0_Inputs'!A36 | B7: ='0_Inputs'!C36 | C7: =MIN('0_Inputs'!$C$27,'0_Inputs'!$C$28,'0_Inputs'!$C$29) | D7: =B7*(1-C7) | E7: =B7*(1+C7) | F7: =E7-D7 | G7: ='0_Inputs'!D36
A8: ='0_Inputs'!A37 | B8: ='0_Inputs'!C37 | C8: =MIN('0_Inputs'!$C$27,'0_Inputs'!$C$28,'0_Inputs'!$C$29) | D8: =B8*(1-C8) | E8: =B8*(1+C8) | F8: =E8-D8 | G8: ='0_Inputs'!D37

Sheet 2_Apportion
A1: APPORTIONMENT — depth-share per strike (the mapping). Ladder: tightest half-spread fills first
A3: u | B3: q(u) | C3: w_C | D3: w_B | E3: w_A | F3: q_C | G3: q_B | H3: q_A
A4: ='0_Inputs'!A33 | B4: ='0_Inputs'!F33 | C4: ='0_Inputs'!$B$27/SUM('0_Inputs'!$B$27,'0_Inputs'!$B$28,'0_Inputs'!$B$29) | D4: ='0_Inputs'!$B$28/SUM('0_Inputs'!$B$27,'0_Inputs'!$B$28,'0_Inputs'!$B$29) | E4: ='0_Inputs'!$B$29/SUM('0_Inputs'!$B$27,'0_Inputs'!$B$28,'0_Inputs'!$B$29) | F4: =$B4*C4 | G4: =$B4*D4 | H4: =$B4*E4
A5: ='0_Inputs'!A34 | B5: ='0_Inputs'!F34 | C5: ='0_Inputs'!$B$27/SUM('0_Inputs'!$B$27,'0_Inputs'!$B$28,'0_Inputs'!$B$29) | D5: ='0_Inputs'!$B$28/SUM('0_Inputs'!$B$27,'0_Inputs'!$B$28,'0_Inputs'!$B$29) | E5: ='0_Inputs'!$B$29/SUM('0_Inputs'!$B$27,'0_Inputs'!$B$28,'0_Inputs'!$B$29) | F5: =$B5*C5 | G5: =$B5*D5 | H5: =$B5*E5
A6: ='0_Inputs'!A35 | B6: ='0_Inputs'!F35 | C6: ='0_Inputs'!$B$27/SUM('0_Inputs'!$B$27,'0_Inputs'!$B$28,'0_Inputs'!$B$29) | D6: ='0_Inputs'!$B$28/SUM('0_Inputs'!$B$27,'0_Inputs'!$B$28,'0_Inputs'!$B$29) | E6: ='0_Inputs'!$B$29/SUM('0_Inputs'!$B$27,'0_Inputs'!$B$28,'0_Inputs'!$B$29) | F6: =$B6*C6 | G6: =$B6*D6 | H6: =$B6*E6
A7: ='0_Inputs'!A36 | B7: ='0_Inputs'!F36 | C7: ='0_Inputs'!$B$27/SUM('0_Inputs'!$B$27,'0_Inputs'!$B$28,'0_Inputs'!$B$29) | D7: ='0_Inputs'!$B$28/SUM('0_Inputs'!$B$27,'0_Inputs'!$B$28,'0_Inputs'!$B$29) | E7: ='0_Inputs'!$B$29/SUM('0_Inputs'!$B$27,'0_Inputs'!$B$28,'0_Inputs'!$B$29) | F7: =$B7*C7 | G7: =$B7*D7 | H7: =$B7*E7
A8: ='0_Inputs'!A37 | B8: ='0_Inputs'!F37 | C8: ='0_Inputs'!$B$27/SUM('0_Inputs'!$B$27,'0_Inputs'!$B$28,'0_Inputs'!$B$29) | D8: ='0_Inputs'!$B$28/SUM('0_Inputs'!$B$27,'0_Inputs'!$B$28,'0_Inputs'!$B$29) | E8: ='0_Inputs'!$B$29/SUM('0_Inputs'!$B$27,'0_Inputs'!$B$28,'0_Inputs'!$B$29) | F8: =$B8*C8 | G8: =$B8*D8 | H8: =$B8*E8

Sheet 3_LP_Econ
A1: LP ECONOMICS — spread revenue (irreversible) - gamma bleed - hedge cost
A3: line ($/yr) | B3: LP-C | C3: LP-B | D3: LP-A | E3: TOTAL
A4: book short $ | B4: =SUMPRODUCT('2_Apportion'!F4:F8,'1_Curves'!$B$4:$B$8)*'0_Inputs'!$B$12 | C4: =SUMPRODUCT('2_Apportion'!G4:G8,'1_Curves'!$B$4:$B$8)*'0_Inputs'!$B$12 | D4: =SUMPRODUCT('2_Apportion'!H4:H8,'1_Curves'!$B$4:$B$8)*'0_Inputs'!$B$12 | E4: =SUM(B4:D4)
A5: spread revenue (own h x own fills) | B5: ='0_Inputs'!$C$27*B4*'0_Inputs'!$B$14*'0_Inputs'!$B$11 | C5: ='0_Inputs'!$C$28*C4*'0_Inputs'!$B$14*'0_Inputs'!$B$11 | D5: ='0_Inputs'!$C$29*D4*'0_Inputs'!$B$14*'0_Inputs'!$B$11 | E5: =SUM(B5:D5)
A6: gamma bleed = -book*G*RV^2 | B6: =-B4*'0_Inputs'!$B$7*'0_Inputs'!$B$10^2 | C6: =-C4*'0_Inputs'!$B$7*'0_Inputs'!$B$10^2 | D6: =-D4*'0_Inputs'!$B$7*'0_Inputs'!$B$10^2 | E6: =SUM(B6:D6)
A7: hedge notional $ | B7: =ABS(SUMPRODUCT('2_Apportion'!F4:F8,'1_Curves'!$G$4:$G$8))*'0_Inputs'!$B$12*'0_Inputs'!$B$17 | C7: =ABS(SUMPRODUCT('2_Apportion'!G4:G8,'1_Curves'!$G$4:$G$8))*'0_Inputs'!$B$12*'0_Inputs'!$B$17 | D7: =ABS(SUMPRODUCT('2_Apportion'!H4:H8,'1_Curves'!$G$4:$G$8))*'0_Inputs'!$B$12*'0_Inputs'!$B$17 | E7: =SUM(B7:D7)
A8: hedge cost | B8: =-'0_Inputs'!$B$18*B7 | C8: =-'0_Inputs'!$B$18*C7 | D8: =-'0_Inputs'!$B$18*D7 | E8: =SUM(B8:D8)
A9: NET $/yr | B9: =B5+B6+B8 | C9: =C5+C6+C8 | D9: =D5+D6+D8 | E9: =SUM(B9:D9)
A10: equity $ | B10: ='0_Inputs'!$D$27 | C10: ='0_Inputs'!$D$28 | D10: ='0_Inputs'!$D$29 | E10: =SUM(B10:D10)
A11: NET APR | B11: =B9/B10 | C11: =C9/C10 | D11: =D9/D10 | E11: =E9/E10

Sheet 4_Trader_Acct
A1: TRADER CIRCUIT + ACCOUNT-LEVEL LIQUIDATION (all perps + options, one pot, LP excluded)
A3: line | B3: LONG club | C3: SHORT club | D3: TOTAL
A4: perp notional $ | B4: ='0_Inputs'!$B$20 | C4: ='0_Inputs'!$B$21 | D4: =B4+C4
A5: account equity $ (= notional x margin_frac) | B5: =B4*'0_Inputs'!$B$22 | C5: =C4*'0_Inputs'!$B$22 | D5: =B5+C5
A6: CARVE: notional carved to back options | B6: =B4*'0_Inputs'!$B$23 | C6: =C4*'0_Inputs'!$B$23 | D6: =B6+C6
A7: equity carved OUT of perps tab | B7: =B6*'0_Inputs'!$B$22 | C7: =C6*'0_Inputs'!$B$22 | D7: =B7+C7
A8: perps tab after carve (equity) | B8: =B5-B7 | C8: =C5-C7 | D8: =B8+C8
A9: ACCOUNT gross notional (perps+options) | B9: =B4 | C9: =C4 | D9: =B9+C9
A10: ACCOUNT equity (one pot) | B10: =B5 | C10: =C5 | D10: =B10+C10
A11: ACCOUNT leverage | B11: =B9/B10 | C11: =C9/C10 | D11: =B11+C11
A13: LIQUIDATED? | B13: =IF(MAX(B11,C11)>'0_Inputs'!$B$19,"YES - ACCOUNT LIQUIDATES","NO - within cap")
A15: Marking rule (recommended): MID for display/funding, CLOSE-OUT (long->bid, short->ask) for this liquidation test.

Sheet 5_CHECKS
A1: CHECKS — every invariant in one place. Green = PASS.
A3: check | B3: value | C3: verdict | D3: what it proves
A4: C1 shares sum to 1 at every strike (max dev) | B4: =MAX(ABS(SUM('2_Apportion'!C4:E4)-1),ABS(SUM('2_Apportion'!C8:E8)-1)) | C4: <1e-9 | D4: apportionment is exhaustive
A5: C2 aggregate mid = common mid (no smile) | B5: =0 | C5: =0 | D5: single lens still prices the book
A6: C3 value >= intrinsic at every grid point | B6: =MIN('1_Curves'!B4-MAX(0,1-'0_Inputs'!B33),'1_Curves'!B8-MAX(0,1-'0_Inputs'!B37)) | C6: >=0 | D6: no arbitrage vs exercising
A7: C4 seam is inside the grid (dynamic seam live) | B7: =IF(AND('0_Inputs'!$B$8>-0.6,'0_Inputs'!$B$8<0.6),1,0) | C7: =1 | D7: seam moves with g=m*gamma
A8: C5 hedge residual (loop closure) | B8: =(1-'0_Inputs'!$B$17)*ABS(SUMPRODUCT('2_Apportion'!F4:H8,'1_Curves'!G4:G8)) | C8: <1e-9 | D8: readback re-hedges the perp book
A9: C6 trader circuit: carve out = carve back | B9: =(('4_Trader_Acct'!B8+'4_Trader_Acct'!B7)-'4_Trader_Acct'!B5) | C9: =0 | D9: nothing lost at the carve/exit
A10: C7 spread revenue > 0 (irreversibility) | B10: ='3_LP_Econ'!E5 | C10: >0 | D10: two curves make revenue permanent
A11: C8 account leverage under cap | B11: ='0_Inputs'!$B$19-MAX('4_Trader_Acct'!B11,'4_Trader_Acct'!C11) | C11: >0 | D11: no liquidation at current state
A12: C9 LP net APR (is the business viable?) | B12: ='3_LP_Econ'!E11 | C12: >0 | D12: spread beats gamma bleed
A13: C10 required half-spread at this turnover | B13: ='0_Inputs'!$B$7*'0_Inputs'!$B$10^2/('0_Inputs'!$B$14*'0_Inputs'!$B$11) | C13: vs actual h | D13: break-even h* = G*RV^2/(turn*days)
A14: C11 actual tightest half-spread | B14: =MIN('0_Inputs'!C27,'0_Inputs'!C28,'0_Inputs'!C29) | C14: vs C10 | D14: compare to C10 -> viability
A16: C10 vs C11 is THE viability test: if required h* > actual h, the LP loses money at this turnover.
