Workbook

Sheet READ_ME
A1: Temporal LP economics — editable model (v1, BRAINSTORM / non-core)
A3: Purpose: does a Temporal LP make money, and under what conditions? For a given trading volume
A4: (per $ of pool notional) and volatility, what yearly return does the LP earn — base vs HLP-restaked.
A6: HOW TO USE: edit the YELLOW cells on 'Assumptions'. Everything recomputes. Open in Excel / Google Sheets / LibreOffice.
A8: THE MODEL (disclosed, per $ notional, annualized):
A9: Fee income = fee_bps/10000 x daily_turnover x days_per_year
A10: Funding = funding_APR [PLACEHOLDER for the update-2 funding formula — edit freely]
A11: LVR cost = (sigma^2/8) x (1 - protection_factor) [sigma^2/8 = classic 50/50 CPMM LVR]
A12: Drain cost = drain_coeff x daily_turnover [small IL-like open->close pool drift]
A13: BASE net APR = Fee + Funding - LVR - Drain
A14: RESTAKED = Base + HLP_base_APR x (1 - HLP_tail_haircut x sigma) [HLP-margin additive layer]
A16: HONESTY LABELS:
... A21: - Reduced-form sketch for intuition, NOT a validated backtest. Lives in sims/ (non-core).

Sheet Assumptions
A1: EDITABLE ASSUMPTIONS
A3: Assumption | B3: Value | C3: Disclosure / note (edit the yellow Value cells)
A4: days_per_year | B4: 365 | C4: trading days/year to annualize
A5: fee_bps | B5: 5 | C5: taker fee, bps of notional traded. Set 0 if Temporal charges no fee (TBD).
A6: funding_APR | B6: 0.03 | C6: NET funding income to the LP per year (PLACEHOLDER for update-2 formula). The main edge vs a vanilla AMM.
A7: protection_factor | B7: 0.5 | C7: fraction of LVR removed by warp+funding tether. 0=pure CPMM loss, 1=LVR gone. HYPOTHESIS.
A8: drain_coeff | B8: 0.005 | C8: round-trip pool drain (IL-like), APR per 1.0 daily turnover. Small.
A9: HLP_base_APR | B9: 0.1 | C9: yield on HLP if LP posts HLP as margin instead of dollars (external input).
A10: HLP_tail_haircut | B10: 0 | C10: 0=pure additive (operator's simple layer); >0 shaves HLP yield as vol rises (crash co-movement).
A13: Grid axes (editable):
A14: daily_turnover -> | B14: 0.25 | C14: 0.5 | D14: 1 | E14: 2 | F14: 5
A15: sigma (annualized) -> | B15: 0.2 | C15: 0.4 | D15: 0.6 | E15: 0.9 | F15: 1.2

Sheet Regime_Grid
A1: BASE LP — net yield APR. GREEN=makes money, RED=loses.
A2: sigma \ turnover(/day) | B2: =Assumptions!B$14 | C2: =Assumptions!C$14 | D2: =Assumptions!D$14 | E2: =Assumptions!E$14 | F2: =Assumptions!F$14
A3: =Assumptions!B$15 | B3: =(Assumptions!$B$5/10000*B$2*Assumptions!$B$4)+Assumptions!$B$6-(($A3^2)/8)*(1-Assumptions!$B$7)-Assumptions!$B$8*B$2 | C3: =(Assumptions!$B$5/10000*C$2*Assumptions!$B$4)+Assumptions!$B$6-(($A3^2)/8)*(1-Assumptions!$B$7)-Assumptions!$B$8*C$2 | D3: =(Assumptions!$B$5/10000*D$2*Assumptions!$B$4)+Assumptions!$B$6-(($A3^2)/8)*(1-Assumptions!$B$7)-Assumptions!$B$8*D$2 | E3: =(Assumptions!$B$5/10000*E$2*Assumptions!$B$4)+Assumptions!$B$6-(($A3^2)/8)*(1-Assumptions!$B$7)-Assumptions!$B$8*E$2 | F3: =(Assumptions!$B$5/10000*F$2*Assumptions!$B$4)+Assumptions!$B$6-(($A3^2)/8)*(1-Assumptions!$B$7)-Assumptions!$B$8*F$2
A4: =Assumptions!C$15 | B4: =(Assumptions!$B$5/10000*B$2*Assumptions!$B$4)+Assumptions!$B$6-(($A4^2)/8)*(1-Assumptions!$B$7)-Assumptions!$B$8*B$2 | C4: =(Assumptions!$B$5/10000*C$2*Assumptions!$B$4)+Assumptions!$B$6-(($A4^2)/8)*(1-Assumptions!$B$7)-Assumptions!$B$8*C$2 | D4: =(Assumptions!$B$5/10000*D$2*Assumptions!$B$4)+Assumptions!$B$6-(($A4^2)/8)*(1-Assumptions!$B$7)-Assumptions!$B$8*D$2 | E4: =(Assumptions!$B$5/10000*E$2*Assumptions!$B$4)+Assumptions!$B$6-(($A4^2)/8)*(1-Assumptions!$B$7)-Assumptions!$B$8*E$2 | F4: =(Assumptions!$B$5/10000*F$2*Assumptions!$B$4)+Assumptions!$B$6-(($A4^2)/8)*(1-Assumptions!$B$7)-Assumptions!$B$8*F$2
A5: =Assumptions!D$15 | B5: =(Assumptions!$B$5/10000*B$2*Assumptions!$B$4)+Assumptions!$B$6-(($A5^2)/8)*(1-Assumptions!$B$7)-Assumptions!$B$8*B$2 | C5: =(Assumptions!$B$5/10000*C$2*Assumptions!$B$4)+Assumptions!$B$6-(($A5^2)/8)*(1-Assumptions!$B$7)-Assumptions!$B$8*C$2 | D5: =(Assumptions!$B$5/10000*D$2*Assumptions!$B$4)+Assumptions!$B$6-(($A5^2)/8)*(1-Assumptions!$B$7)-Assumptions!$B$8*D$2 | E5: =(Assumptions!$B$5/10000*E$2*Assumptions!$B$4)+Assumptions!$B$6-(($A5^2)/8)*(1-Assumptions!$B$7)-Assumptions!$B$8*E$2 | F5: =(Assumptions!$B$5/10000*F$2*Assumptions!$B$4)+Assumptions!$B$6-(($A5^2)/8)*(1-Assumptions!$B$7)-Assumptions!$B$8*F$2
A6: =Assumptions!E$15 | B6: =(Assumptions!$B$5/10000*B$2*Assumptions!$B$4)+Assumptions!$B$6-(($A6^2)/8)*(1-Assumptions!$B$7)-Assumptions!$B$8*B$2 | C6: =(Assumptions!$B$5/10000*C$2*Assumptions!$B$4)+Assumptions!$B$6-(($A6^2)/8)*(1-Assumptions!$B$7)-Assumptions!$B$8*C$2 | D6: =(Assumptions!$B$5/10000*D$2*Assumptions!$B$4)+Assumptions!$B$6-(($A6^2)/8)*(1-Assumptions!$B$7)-Assumptions!$B$8*D$2 | E6: =(Assumptions!$B$5/10000*E$2*Assumptions!$B$4)+Assumptions!$B$6-(($A6^2)/8)*(1-Assumptions!$B$7)-Assumptions!$B$8*E$2 | F6: =(Assumptions!$B$5/10000*F$2*Assumptions!$B$4)+Assumptions!$B$6-(($A6^2)/8)*(1-Assumptions!$B$7)-Assumptions!$B$8*F$2
A7: =Assumptions!F$15 | B7: =(Assumptions!$B$5/10000*B$2*Assumptions!$B$4)+Assumptions!$B$6-(($A7^2)/8)*(1-Assumptions!$B$7)-Assumptions!$B$8*B$2 | C7: =(Assumptions!$B$5/10000*C$2*Assumptions!$B$4)+Assumptions!$B$6-(($A7^2)/8)*(1-Assumptions!$B$7)-Assumptions!$B$8*C$2 | D7: =(Assumptions!$B$5/10000*D$2*Assumptions!$B$4)+Assumptions!$B$6-(($A7^2)/8)*(1-Assumptions!$B$7)-Assumptions!$B$8*D$2 | E7: =(Assumptions!$B$5/10000*E$2*Assumptions!$B$4)+Assumptions!$B$6-(($A7^2)/8)*(1-Assumptions!$B$7)-Assumptions!$B$8*E$2 | F7: =(Assumptions!$B$5/10000*F$2*Assumptions!$B$4)+Assumptions!$B$6-(($A7^2)/8)*(1-Assumptions!$B$7)-Assumptions!$B$8*F$2
A10: RESTAKED LP (HLP-margined) — net yield APR.
A11: sigma \ turnover(/day) | B11: =Assumptions!B$14 | C11: =Assumptions!C$14 | D11: =Assumptions!D$14 | E11: =Assumptions!E$14 | F11: =Assumptions!F$14
A12: =Assumptions!B$15 | B12: =((Assumptions!$B$5/10000*B$11*Assumptions!$B$4)+Assumptions!$B$6-(($A12^2)/8)*(1-Assumptions!$B$7)-Assumptions!$B$8*B$11)+Assumptions!$B$9*(1-Assumptions!$B$10*$A12) | C12: =((Assumptions!$B$5/10000*C$11*Assumptions!$B$4)+Assumptions!$B$6-(($A12^2)/8)*(1-Assumptions!$B$7)-Assumptions!$B$8*C$11)+Assumptions!$B$9*(1-Assumptions!$B$10*$A12) | D12: =((Assumptions!$B$5/10000*D$11*Assumptions!$B$4)+Assumptions!$B$6-(($A12^2)/8)*(1-Assumptions!$B$7)-Assumptions!$B$8*D$11)+Assumptions!$B$9*(1-Assumptions!$B$10*$A12) | E12: =((Assumptions!$B$5/10000*E$11*Assumptions!$B$4)+Assumptions!$B$6-(($A12^2)/8)*(1-Assumptions!$B$7)-Assumptions!$B$8*E$11)+Assumptions!$B$9*(1-Assumptions!$B$10*$A12) | F12: =((Assumptions!$B$5/10000*F$11*Assumptions!$B$4)+Assumptions!$B$6-(($A12^2)/8)*(1-Assumptions!$B$7)-Assumptions!$B$8*F$11)+Assumptions!$B$9*(1-Assumptions!$B$10*$A12)
A13: =Assumptions!C$15 | B13: =((Assumptions!$B$5/10000*B$11*Assumptions!$B$4)+Assumptions!$B$6-(($A13^2)/8)*(1-Assumptions!$B$7)-Assumptions!$B$8*B$11)+Assumptions!$B$9*(1-Assumptions!$B$10*$A13) | C13: =((Assumptions!$B$5/10000*C$11*Assumptions!$B$4)+Assumptions!$B$6-(($A13^2)/8)*(1-Assumptions!$B$7)-Assumptions!$B$8*C$11)+Assumptions!$B$9*(1-Assumptions!$B$10*$A13) | D13: =((Assumptions!$B$5/10000*D$11*Assumptions!$B$4)+Assumptions!$B$6-(($A13^2)/8)*(1-Assumptions!$B$7)-Assumptions!$B$8*D$11)+Assumptions!$B$9*(1-Assumptions!$B$10*$A13) | E13: =((Assumptions!$B$5/10000*E$11*Assumptions!$B$4)+Assumptions!$B$6-(($A13^2)/8)*(1-Assumptions!$B$7)-Assumptions!$B$8*E$11)+Assumptions!$B$9*(1-Assumptions!$B$10*$A13) | F13: =((Assumptions!$B$5/10000*F$11*Assumptions!$B$4)+Assumptions!$B$6-(($A13^2)/8)*(1-Assumptions!$B$7)-Assumptions!$B$8*F$11)+Assumptions!$B$9*(1-Assumptions!$B$10*$A13)
A14: =Assumptions!D$15 | B14: =((Assumptions!$B$5/10000*B$11*Assumptions!$B$4)+Assumptions!$B$6-(($A14^2)/8)*(1-Assumptions!$B$7)-Assumptions!$B$8*B$11)+Assumptions!$B$9*(1-Assumptions!$B$10*$A14) | C14: =((Assumptions!$B$5/10000*C$11*Assumptions!$B$4)+Assumptions!$B$6-(($A14^2)/8)*(1-Assumptions!$B$7)-Assumptions!$B$8*C$11)+Assumptions!$B$9*(1-Assumptions!$B$10*$A14) | D14: =((Assumptions!$B$5/10000*D$11*Assumptions!$B$4)+Assumptions!$B$6-(($A14^2)/8)*(1-Assumptions!$B$7)-Assumptions!$B$8*D$11)+Assumptions!$B$9*(1-Assumptions!$B$10*$A14) | E14: =((Assumptions!$B$5/10000*E$11*Assumptions!$B$4)+Assumptions!$B$6-(($A14^2)/8)*(1-Assumptions!$B$7)-Assumptions!$B$8*E$11)+Assumptions!$B$9*(1-Assumptions!$B$10*$A14) | F14: =((Assumptions!$B$5/10000*F$11*Assumptions!$B$4)+Assumptions!$B$6-(($A14^2)/8)*(1-Assumptions!$B$7)-Assumptions!$B$8*F$11)+Assumptions!$B$9*(1-Assumptions!$B$10*$A14)
A15: =Assumptions!E$15 | B15: =((Assumptions!$B$5/10000*B$11*Assumptions!$B$4)+Assumptions!$B$6-(($A15^2)/8)*(1-Assumptions!$B$7)-Assumptions!$B$8*B$11)+Assumptions!$B$9*(1-Assumptions!$B$10*$A15) | C15: =((Assumptions!$B$5/10000*C$11*Assumptions!$B$4)+Assumptions!$B$6-(($A15^2)/8)*(1-Assumptions!$B$7)-Assumptions!$B$8*C$11)+Assumptions!$B$9*(1-Assumptions!$B$10*$A15) | D15: =((Assumptions!$B$5/10000*D$11*Assumptions!$B$4)+Assumptions!$B$6-(($A15^2)/8)*(1-Assumptions!$B$7)-Assumptions!$B$8*D$11)+Assumptions!$B$9*(1-Assumptions!$B$10*$A15) | E15: =((Assumptions!$B$5/10000*E$11*Assumptions!$B$4)+Assumptions!$B$6-(($A15^2)/8)*(1-Assumptions!$B$7)-Assumptions!$B$8*E$11)+Assumptions!$B$9*(1-Assumptions!$B$10*$A15) | F15: =((Assumptions!$B$5/10000*F$11*Assumptions!$B$4)+Assumptions!$B$6-(($A15^2)/8)*(1-Assumptions!$B$7)-Assumptions!$B$8*F$11)+Assumptions!$B$9*(1-Assumptions!$B$10*$A15)
A16: =Assumptions!F$15 | B16: =((Assumptions!$B$5/10000*B$11*Assumptions!$B$4)+Assumptions!$B$6-(($A16^2)/8)*(1-Assumptions!$B$7)-Assumptions!$B$8*B$11)+Assumptions!$B$9*(1-Assumptions!$B$10*$A16) | C16: =((Assumptions!$B$5/10000*C$11*Assumptions!$B$4)+Assumptions!$B$6-(($A16^2)/8)*(1-Assumptions!$B$7)-Assumptions!$B$8*C$11)+Assumptions!$B$9*(1-Assumptions!$B$10*$A16) | D16: =((Assumptions!$B$5/10000*D$11*Assumptions!$B$4)+Assumptions!$B$6-(($A16^2)/8)*(1-Assumptions!$B$7)-Assumptions!$B$8*D$11)+Assumptions!$B$9*(1-Assumptions!$B$10*$A16) | E16: =((Assumptions!$B$5/10000*E$11*Assumptions!$B$4)+Assumptions!$B$6-(($A16^2)/8)*(1-Assumptions!$B$7)-Assumptions!$B$8*E$11)+Assumptions!$B$9*(1-Assumptions!$B$10*$A16) | F16: =((Assumptions!$B$5/10000*F$11*Assumptions!$B$4)+Assumptions!$B$6-(($A16^2)/8)*(1-Assumptions!$B$7)-Assumptions!$B$8*F$11)+Assumptions!$B$9*(1-Assumptions!$B$10*$A16)
A19: Break-even = the green/red boundary: trading volume needed at each vol for LPs to be net-positive.

Sheet Scenario_calc
A1: SINGLE-SCENARIO BREAKDOWN (edit the two yellow inputs)
A3: daily_turnover | B3: 1
A4: sigma (annualized) | B4: 0.6
A6: Fee income (APR) | B6: =Assumptions!$B$5/10000*$B$3*Assumptions!$B$4 | C6: turnover x fee, annualized
A7: Funding income (APR) | B7: =Assumptions!$B$6 | C7: placeholder — update-2
A8: LVR cost (APR) | B8: =-(($B$4^2)/8)*(1-Assumptions!$B$7) | C8: sigma^2/8 x (1-protection)
A9: Round-trip drain (APR) | B9: =-Assumptions!$B$8*$B$3 | C9: IL-like open->close
A10: BASE LP net (APR) | B10: =B6+B7+B8+B9 | C10: sum above
A11: HLP layer (APR) | B11: =Assumptions!$B$9*(1-Assumptions!$B$10*$B$4) | C11: additive minus tail haircut
A12: RESTAKED LP net (APR) | B12: =B10+B11 | C12: base + HLP
