Workbook

Sheet READ_ME
A1: Temporal LP economics — FAITHFUL perp-OPTIONS-AMM model (v4, auditor-corrected) — BRAINSTORM / non-core
A2: Temporal LP economics — FAITHFUL perp-OPTIONS-AMM model (v4, auditor-corrected) — BRAINSTORM / non-core
A3: The LP SELLS the perpetual-option book (the bands), delta-hedged on Hyperliquid ⇒ SHORT-VOL. For a PERPETUAL there is
A4: no upfront premium: the long's continuous FUNDING = the carry the LP collects. The LP's edge = that carry minus the
A5: realized-vol gamma cost. It profits when realized vol < the vol the curve is CALIBRATED to.
A7: MODEL (per $ LP equity, annualized) — ONE carry line (no separate premium+funding double-count):
A8: G = (m*gamma)*(m*gamma+1)/2 <- LENSED gamma factor of value∝S^(-m*gamma); the steepness knob m IS in it now
A9: options_net = book * G * (sigma_cal^2 - RV^2) = funding-carry(priced at sigma_cal) MINUS realized gamma bleed
A10: BASE = options_net + fee_bps/10000*turnover*days*book - (book-1)*borrow_APR - hedge_fee_cost + book*hedge_funding_APR
A11: RESTAKED = BASE + HLP_base_APR*(1 - HLP_tail_haircut*RV)
A13: WHAT THE AUDITOR (opus) FIXED vs v3:
A14: 1. DOUBLE-COUNT removed: v3 had a VRP line AND a separate funding_APR — same perpetual carry twice. Now ONE carry line.
... A21: - sigma_cal>RV is an operator CALIBRATION / flow bet, not an automatic variance risk premium. Reduced-form sketch, not a backtest.

Sheet Assumptions
A1: EDITABLE ASSUMPTIONS (edit yellow cells; everything recomputes)
A3: Assumption | B3: Value | C3: Disclosure / note
A4: days_per_year | B4: 365 | C4: annualization
A5: gamma_curve | B5: 2 | C5: base gamma of value∝S^(-gamma).
A6: m_steepness | B6: 1 | C6: the kurtosis/steepness knob. Lensed exponent = m*gamma. Enters the gamma factor G=(m*gamma)(m*gamma+1)/2.
A7: LP_leverage | B7: 1 | C7: LEVERAGE on the Temporal/options side = option value short per $ of equity (1.0x = unlevered). HLP is additive at margin and NOT levered (per entry 486). borrow_APR below is its financing cost.
A8: daily_turnover | B8: 1 | C8: volume / notional per day (fee income).
A9: fee_bps | B9: 5 | C9: taker fee, bps of notional traded.
A10: borrow_APR | B10: 0.06 | C10: financing on the (book-1) leveraged portion.
A11: hedge_fee_cost | B11: 0 | C11: net fee cost of the HL delta hedge (~0 fee-neutral).
A12: hedge_funding_APR | B12: 0 | C12: funding on the HL hedge legs, +/- (default 0).
A13: HLP_base_APR | B13: 0.1 | C13: yield on HLP margin (additive, NOT levered).
A14: HLP_tail_haircut | B14: 0 | C14: 0=pure additive; >0 shaves HLP as RV rises.
A15: Grid axes (editable):
A16: realized_vol RV (grid ROWS) -> | B16: 0.2 | C16: 0.4 | D16: 0.6 | E16: 0.8 | F16: 1
A17: sigma_cal calibration vol (grid COLS) -> | B17: 0.3 | C17: 0.5 | D17: 0.7 | E17: 0.9 | F17: 1.1
A19: Legend: yellow=editable. G=(m*gamma)(m*gamma+1)/2. options_net=book*G*(sigma_cal^2-RV^2).

Sheet Regime_Grid
A1: REGIME GRID — net LP yield APR. rows=REALIZED vol, cols=CALIBRATION vol. green=profit / red=loss.
A3: BASE — options-seller LP net APR (dollar margin).
A4: RV \ sigma_cal | B4: =Assumptions!B$17 | C4: =Assumptions!C$17 | D4: =Assumptions!D$17 | E4: =Assumptions!E$17 | F4: =Assumptions!F$17
A5: =Assumptions!B$16 | B5: =Assumptions!$B$7*((Assumptions!$B$6*Assumptions!$B$5)*((Assumptions!$B$6*Assumptions!$B$5)+1)/2)*((B$4)^2-($A5)^2)+Assumptions!$B$9/10000*Assumptions!$B$8*Assumptions!$B$4*Assumptions!$B$7-(Assumptions!$B$7-1)*Assumptions!$B$10-Assumptions!$B$11+Assumptions!$B$7*Assumptions!$B$12 | C5: =Assumptions!$B$7*((Assumptions!$B$6*Assumptions!$B$5)*((Assumptions!$B$6*Assumptions!$B$5)+1)/2)*((C$4)^2-($A5)^2)+Assumptions!$B$9/10000*Assumptions!$B$8*Assumptions!$B$4*Assumptions!$B$7-(Assumptions!$B$7-1)*Assumptions!$B$10-Assumptions!$B$11+Assumptions!$B$7*Assumptions!$B$12 | D5: =Assumptions!$B$7*((Assumptions!$B$6*Assumptions!$B$5)*((Assumptions!$B$6*Assumptions!$B$5)+1)/2)*((D$4)^2-($A5)^2)+Assumptions!$B$9/10000*Assumptions!$B$8*Assumptions!$B$4*Assumptions!$B$7-(Assumptions!$B$7-1)*Assumptions!$B$10-Assumptions!$B$11+Assumptions!$B$7*Assumptions!$B$12 | E5: =Assumptions!$B$7*((Assumptions!$B$6*Assumptions!$B$5)*((Assumptions!$B$6*Assumptions!$B$5)+1)/2)*((E$4)^2-($A5)^2)+Assumptions!$B$9/10000*Assumptions!$B$8*Assumptions!$B$4*Assumptions!$B$7-(Assumptions!$B$7-1)*Assumptions!$B$10-Assumptions!$B$11+Assumptions!$B$7*Assumptions!$B$12 | F5: =Assumptions!$B$7*((Assumptions!$B$6*Assumptions!$B$5)*((Assumptions!$B$6*Assumptions!$B$5)+1)/2)*((F$4)^2-($A5)^2)+Assumptions!$B$9/10000*Assumptions!$B$8*Assumptions!$B$4*Assumptions!$B$7-(Assumptions!$B$7-1)*Assumptions!$B$10-Assumptions!$B$11+Assumptions!$B$7*Assumptions!$B$12
A6: =Assumptions!C$16 | B6: =Assumptions!$B$7*((Assumptions!$B$6*Assumptions!$B$5)*((Assumptions!$B$6*Assumptions!$B$5)+1)/2)*((B$4)^2-($A6)^2)+Assumptions!$B$9/10000*Assumptions!$B$8*Assumptions!$B$4*Assumptions!$B$7-(Assumptions!$B$7-1)*Assumptions!$B$10-Assumptions!$B$11+Assumptions!$B$7*Assumptions!$B$12 | C6: =Assumptions!$B$7*((Assumptions!$B$6*Assumptions!$B$5)*((Assumptions!$B$6*Assumptions!$B$5)+1)/2)*((C$4)^2-($A6)^2)+Assumptions!$B$9/10000*Assumptions!$B$8*Assumptions!$B$4*Assumptions!$B$7-(Assumptions!$B$7-1)*Assumptions!$B$10-Assumptions!$B$11+Assumptions!$B$7*Assumptions!$B$12 | D6: =Assumptions!$B$7*((Assumptions!$B$6*Assumptions!$B$5)*((Assumptions!$B$6*Assumptions!$B$5)+1)/2)*((D$4)^2-($A6)^2)+Assumptions!$B$9/10000*Assumptions!$B$8*Assumptions!$B$4*Assumptions!$B$7-(Assumptions!$B$7-1)*Assumptions!$B$10-Assumptions!$B$11+Assumptions!$B$7*Assumptions!$B$12 | E6: =Assumptions!$B$7*((Assumptions!$B$6*Assumptions!$B$5)*((Assumptions!$B$6*Assumptions!$B$5)+1)/2)*((E$4)^2-($A6)^2)+Assumptions!$B$9/10000*Assumptions!$B$8*Assumptions!$B$4*Assumptions!$B$7-(Assumptions!$B$7-1)*Assumptions!$B$10-Assumptions!$B$11+Assumptions!$B$7*Assumptions!$B$12 | F6: =Assumptions!$B$7*((Assumptions!$B$6*Assumptions!$B$5)*((Assumptions!$B$6*Assumptions!$B$5)+1)/2)*((F$4)^2-($A6)^2)+Assumptions!$B$9/10000*Assumptions!$B$8*Assumptions!$B$4*Assumptions!$B$7-(Assumptions!$B$7-1)*Assumptions!$B$10-Assumptions!$B$11+Assumptions!$B$7*Assumptions!$B$12
A7: =Assumptions!D$16 | B7: =Assumptions!$B$7*((Assumptions!$B$6*Assumptions!$B$5)*((Assumptions!$B$6*Assumptions!$B$5)+1)/2)*((B$4)^2-($A7)^2)+Assumptions!$B$9/10000*Assumptions!$B$8*Assumptions!$B$4*Assumptions!$B$7-(Assumptions!$B$7-1)*Assumptions!$B$10-Assumptions!$B$11+Assumptions!$B$7*Assumptions!$B$12 | C7: =Assumptions!$B$7*((Assumptions!$B$6*Assumptions!$B$5)*((Assumptions!$B$6*Assumptions!$B$5)+1)/2)*((C$4)^2-($A7)^2)+Assumptions!$B$9/10000*Assumptions!$B$8*Assumptions!$B$4*Assumptions!$B$7-(Assumptions!$B$7-1)*Assumptions!$B$10-Assumptions!$B$11+Assumptions!$B$7*Assumptions!$B$12 | D7: =Assumptions!$B$7*((Assumptions!$B$6*Assumptions!$B$5)*((Assumptions!$B$6*Assumptions!$B$5)+1)/2)*((D$4)^2-($A7)^2)+Assumptions!$B$9/10000*Assumptions!$B$8*Assumptions!$B$4*Assumptions!$B$7-(Assumptions!$B$7-1)*Assumptions!$B$10-Assumptions!$B$11+Assumptions!$B$7*Assumptions!$B$12 | E7: =Assumptions!$B$7*((Assumptions!$B$6*Assumptions!$B$5)*((Assumptions!$B$6*Assumptions!$B$5)+1)/2)*((E$4)^2-($A7)^2)+Assumptions!$B$9/10000*Assumptions!$B$8*Assumptions!$B$4*Assumptions!$B$7-(Assumptions!$B$7-1)*Assumptions!$B$10-Assumptions!$B$11+Assumptions!$B$7*Assumptions!$B$12 | F7: =Assumptions!$B$7*((Assumptions!$B$6*Assumptions!$B$5)*((Assumptions!$B$6*Assumptions!$B$5)+1)/2)*((F$4)^2-($A7)^2)+Assumptions!$B$9/10000*Assumptions!$B$8*Assumptions!$B$4*Assumptions!$B$7-(Assumptions!$B$7-1)*Assumptions!$B$10-Assumptions!$B$11+Assumptions!$B$7*Assumptions!$B$12
A8: =Assumptions!E$16 | B8: =Assumptions!$B$7*((Assumptions!$B$6*Assumptions!$B$5)*((Assumptions!$B$6*Assumptions!$B$5)+1)/2)*((B$4)^2-($A8)^2)+Assumptions!$B$9/10000*Assumptions!$B$8*Assumptions!$B$4*Assumptions!$B$7-(Assumptions!$B$7-1)*Assumptions!$B$10-Assumptions!$B$11+Assumptions!$B$7*Assumptions!$B$12 | C8: =Assumptions!$B$7*((Assumptions!$B$6*Assumptions!$B$5)*((Assumptions!$B$6*Assumptions!$B$5)+1)/2)*((C$4)^2-($A8)^2)+Assumptions!$B$9/10000*Assumptions!$B$8*Assumptions!$B$4*Assumptions!$B$7-(Assumptions!$B$7-1)*Assumptions!$B$10-Assumptions!$B$11+Assumptions!$B$7*Assumptions!$B$12 | D8: =Assumptions!$B$7*((Assumptions!$B$6*Assumptions!$B$5)*((Assumptions!$B$6*Assumptions!$B$5)+1)/2)*((D$4)^2-($A8)^2)+Assumptions!$B$9/10000*Assumptions!$B$8*Assumptions!$B$4*Assumptions!$B$7-(Assumptions!$B$7-1)*Assumptions!$B$10-Assumptions!$B$11+Assumptions!$B$7*Assumptions!$B$12 | E8: =Assumptions!$B$7*((Assumptions!$B$6*Assumptions!$B$5)*((Assumptions!$B$6*Assumptions!$B$5)+1)/2)*((E$4)^2-($A8)^2)+Assumptions!$B$9/10000*Assumptions!$B$8*Assumptions!$B$4*Assumptions!$B$7-(Assumptions!$B$7-1)*Assumptions!$B$10-Assumptions!$B$11+Assumptions!$B$7*Assumptions!$B$12 | F8: =Assumptions!$B$7*((Assumptions!$B$6*Assumptions!$B$5)*((Assumptions!$B$6*Assumptions!$B$5)+1)/2)*((F$4)^2-($A8)^2)+Assumptions!$B$9/10000*Assumptions!$B$8*Assumptions!$B$4*Assumptions!$B$7-(Assumptions!$B$7-1)*Assumptions!$B$10-Assumptions!$B$11+Assumptions!$B$7*Assumptions!$B$12
A9: =Assumptions!F$16 | B9: =Assumptions!$B$7*((Assumptions!$B$6*Assumptions!$B$5)*((Assumptions!$B$6*Assumptions!$B$5)+1)/2)*((B$4)^2-($A9)^2)+Assumptions!$B$9/10000*Assumptions!$B$8*Assumptions!$B$4*Assumptions!$B$7-(Assumptions!$B$7-1)*Assumptions!$B$10-Assumptions!$B$11+Assumptions!$B$7*Assumptions!$B$12 | C9: =Assumptions!$B$7*((Assumptions!$B$6*Assumptions!$B$5)*((Assumptions!$B$6*Assumptions!$B$5)+1)/2)*((C$4)^2-($A9)^2)+Assumptions!$B$9/10000*Assumptions!$B$8*Assumptions!$B$4*Assumptions!$B$7-(Assumptions!$B$7-1)*Assumptions!$B$10-Assumptions!$B$11+Assumptions!$B$7*Assumptions!$B$12 | D9: =Assumptions!$B$7*((Assumptions!$B$6*Assumptions!$B$5)*((Assumptions!$B$6*Assumptions!$B$5)+1)/2)*((D$4)^2-($A9)^2)+Assumptions!$B$9/10000*Assumptions!$B$8*Assumptions!$B$4*Assumptions!$B$7-(Assumptions!$B$7-1)*Assumptions!$B$10-Assumptions!$B$11+Assumptions!$B$7*Assumptions!$B$12 | E9: =Assumptions!$B$7*((Assumptions!$B$6*Assumptions!$B$5)*((Assumptions!$B$6*Assumptions!$B$5)+1)/2)*((E$4)^2-($A9)^2)+Assumptions!$B$9/10000*Assumptions!$B$8*Assumptions!$B$4*Assumptions!$B$7-(Assumptions!$B$7-1)*Assumptions!$B$10-Assumptions!$B$11+Assumptions!$B$7*Assumptions!$B$12 | F9: =Assumptions!$B$7*((Assumptions!$B$6*Assumptions!$B$5)*((Assumptions!$B$6*Assumptions!$B$5)+1)/2)*((F$4)^2-($A9)^2)+Assumptions!$B$9/10000*Assumptions!$B$8*Assumptions!$B$4*Assumptions!$B$7-(Assumptions!$B$7-1)*Assumptions!$B$10-Assumptions!$B$11+Assumptions!$B$7*Assumptions!$B$12
A12: RESTAKED — + HLP margin.
A13: RV \ sigma_cal | B13: =Assumptions!B$17 | C13: =Assumptions!C$17 | D13: =Assumptions!D$17 | E13: =Assumptions!E$17 | F13: =Assumptions!F$17
A14: =Assumptions!B$16 | B14: =(Assumptions!$B$7*((Assumptions!$B$6*Assumptions!$B$5)*((Assumptions!$B$6*Assumptions!$B$5)+1)/2)*((B$13)^2-($A14)^2)+Assumptions!$B$9/10000*Assumptions!$B$8*Assumptions!$B$4*Assumptions!$B$7-(Assumptions!$B$7-1)*Assumptions!$B$10-Assumptions!$B$11+Assumptions!$B$7*Assumptions!$B$12)+Assumptions!$B$13*(1-Assumptions!$B$14*$A14) | C14: =(Assumptions!$B$7*((Assumptions!$B$6*Assumptions!$B$5)*((Assumptions!$B$6*Assumptions!$B$5)+1)/2)*((C$13)^2-($A14)^2)+Assumptions!$B$9/10000*Assumptions!$B$8*Assumptions!$B$4*Assumptions!$B$7-(Assumptions!$B$7-1)*Assumptions!$B$10-Assumptions!$B$11+Assumptions!$B$7*Assumptions!$B$12)+Assumptions!$B$13*(1-Assumptions!$B$14*$A14) | D14: =(Assumptions!$B$7*((Assumptions!$B$6*Assumptions!$B$5)*((Assumptions!$B$6*Assumptions!$B$5)+1)/2)*((D$13)^2-($A14)^2)+Assumptions!$B$9/10000*Assumptions!$B$8*Assumptions!$B$4*Assumptions!$B$7-(Assumptions!$B$7-1)*Assumptions!$B$10-Assumptions!$B$11+Assumptions!$B$7*Assumptions!$B$12)+Assumptions!$B$13*(1-Assumptions!$B$14*$A14) | E14: =(Assumptions!$B$7*((Assumptions!$B$6*Assumptions!$B$5)*((Assumptions!$B$6*Assumptions!$B$5)+1)/2)*((E$13)^2-($A14)^2)+Assumptions!$B$9/10000*Assumptions!$B$8*Assumptions!$B$4*Assumptions!$B$7-(Assumptions!$B$7-1)*Assumptions!$B$10-Assumptions!$B$11+Assumptions!$B$7*Assumptions!$B$12)+Assumptions!$B$13*(1-Assumptions!$B$14*$A14) | F14: =(Assumptions!$B$7*((Assumptions!$B$6*Assumptions!$B$5)*((Assumptions!$B$6*Assumptions!$B$5)+1)/2)*((F$13)^2-($A14)^2)+Assumptions!$B$9/10000*Assumptions!$B$8*Assumptions!$B$4*Assumptions!$B$7-(Assumptions!$B$7-1)*Assumptions!$B$10-Assumptions!$B$11+Assumptions!$B$7*Assumptions!$B$12)+Assumptions!$B$13*(1-Assumptions!$B$14*$A14)
A15: =Assumptions!C$16 | B15: =(Assumptions!$B$7*((Assumptions!$B$6*Assumptions!$B$5)*((Assumptions!$B$6*Assumptions!$B$5)+1)/2)*((B$13)^2-($A15)^2)+Assumptions!$B$9/10000*Assumptions!$B$8*Assumptions!$B$4*Assumptions!$B$7-(Assumptions!$B$7-1)*Assumptions!$B$10-Assumptions!$B$11+Assumptions!$B$7*Assumptions!$B$12)+Assumptions!$B$13*(1-Assumptions!$B$14*$A15) | C15: =(Assumptions!$B$7*((Assumptions!$B$6*Assumptions!$B$5)*((Assumptions!$B$6*Assumptions!$B$5)+1)/2)*((C$13)^2-($A15)^2)+Assumptions!$B$9/10000*Assumptions!$B$8*Assumptions!$B$4*Assumptions!$B$7-(Assumptions!$B$7-1)*Assumptions!$B$10-Assumptions!$B$11+Assumptions!$B$7*Assumptions!$B$12)+Assumptions!$B$13*(1-Assumptions!$B$14*$A15) | D15: =(Assumptions!$B$7*((Assumptions!$B$6*Assumptions!$B$5)*((Assumptions!$B$6*Assumptions!$B$5)+1)/2)*((D$13)^2-($A15)^2)+Assumptions!$B$9/10000*Assumptions!$B$8*Assumptions!$B$4*Assumptions!$B$7-(Assumptions!$B$7-1)*Assumptions!$B$10-Assumptions!$B$11+Assumptions!$B$7*Assumptions!$B$12)+Assumptions!$B$13*(1-Assumptions!$B$14*$A15) | E15: =(Assumptions!$B$7*((Assumptions!$B$6*Assumptions!$B$5)*((Assumptions!$B$6*Assumptions!$B$5)+1)/2)*((E$13)^2-($A15)^2)+Assumptions!$B$9/10000*Assumptions!$B$8*Assumptions!$B$4*Assumptions!$B$7-(Assumptions!$B$7-1)*Assumptions!$B$10-Assumptions!$B$11+Assumptions!$B$7*Assumptions!$B$12)+Assumptions!$B$13*(1-Assumptions!$B$14*$A15) | F15: =(Assumptions!$B$7*((Assumptions!$B$6*Assumptions!$B$5)*((Assumptions!$B$6*Assumptions!$B$5)+1)/2)*((F$13)^2-($A15)^2)+Assumptions!$B$9/10000*Assumptions!$B$8*Assumptions!$B$4*Assumptions!$B$7-(Assumptions!$B$7-1)*Assumptions!$B$10-Assumptions!$B$11+Assumptions!$B$7*Assumptions!$B$12)+Assumptions!$B$13*(1-Assumptions!$B$14*$A15)
A16: =Assumptions!D$16 | B16: =(Assumptions!$B$7*((Assumptions!$B$6*Assumptions!$B$5)*((Assumptions!$B$6*Assumptions!$B$5)+1)/2)*((B$13)^2-($A16)^2)+Assumptions!$B$9/10000*Assumptions!$B$8*Assumptions!$B$4*Assumptions!$B$7-(Assumptions!$B$7-1)*Assumptions!$B$10-Assumptions!$B$11+Assumptions!$B$7*Assumptions!$B$12)+Assumptions!$B$13*(1-Assumptions!$B$14*$A16) | C16: =(Assumptions!$B$7*((Assumptions!$B$6*Assumptions!$B$5)*((Assumptions!$B$6*Assumptions!$B$5)+1)/2)*((C$13)^2-($A16)^2)+Assumptions!$B$9/10000*Assumptions!$B$8*Assumptions!$B$4*Assumptions!$B$7-(Assumptions!$B$7-1)*Assumptions!$B$10-Assumptions!$B$11+Assumptions!$B$7*Assumptions!$B$12)+Assumptions!$B$13*(1-Assumptions!$B$14*$A16) | D16: =(Assumptions!$B$7*((Assumptions!$B$6*Assumptions!$B$5)*((Assumptions!$B$6*Assumptions!$B$5)+1)/2)*((D$13)^2-($A16)^2)+Assumptions!$B$9/10000*Assumptions!$B$8*Assumptions!$B$4*Assumptions!$B$7-(Assumptions!$B$7-1)*Assumptions!$B$10-Assumptions!$B$11+Assumptions!$B$7*Assumptions!$B$12)+Assumptions!$B$13*(1-Assumptions!$B$14*$A16) | E16: =(Assumptions!$B$7*((Assumptions!$B$6*Assumptions!$B$5)*((Assumptions!$B$6*Assumptions!$B$5)+1)/2)*((E$13)^2-($A16)^2)+Assumptions!$B$9/10000*Assumptions!$B$8*Assumptions!$B$4*Assumptions!$B$7-(Assumptions!$B$7-1)*Assumptions!$B$10-Assumptions!$B$11+Assumptions!$B$7*Assumptions!$B$12)+Assumptions!$B$13*(1-Assumptions!$B$14*$A16) | F16: =(Assumptions!$B$7*((Assumptions!$B$6*Assumptions!$B$5)*((Assumptions!$B$6*Assumptions!$B$5)+1)/2)*((F$13)^2-($A16)^2)+Assumptions!$B$9/10000*Assumptions!$B$8*Assumptions!$B$4*Assumptions!$B$7-(Assumptions!$B$7-1)*Assumptions!$B$10-Assumptions!$B$11+Assumptions!$B$7*Assumptions!$B$12)+Assumptions!$B$13*(1-Assumptions!$B$14*$A16)
A17: =Assumptions!E$16 | B17: =(Assumptions!$B$7*((Assumptions!$B$6*Assumptions!$B$5)*((Assumptions!$B$6*Assumptions!$B$5)+1)/2)*((B$13)^2-($A17)^2)+Assumptions!$B$9/10000*Assumptions!$B$8*Assumptions!$B$4*Assumptions!$B$7-(Assumptions!$B$7-1)*Assumptions!$B$10-Assumptions!$B$11+Assumptions!$B$7*Assumptions!$B$12)+Assumptions!$B$13*(1-Assumptions!$B$14*$A17) | C17: =(Assumptions!$B$7*((Assumptions!$B$6*Assumptions!$B$5)*((Assumptions!$B$6*Assumptions!$B$5)+1)/2)*((C$13)^2-($A17)^2)+Assumptions!$B$9/10000*Assumptions!$B$8*Assumptions!$B$4*Assumptions!$B$7-(Assumptions!$B$7-1)*Assumptions!$B$10-Assumptions!$B$11+Assumptions!$B$7*Assumptions!$B$12)+Assumptions!$B$13*(1-Assumptions!$B$14*$A17) | D17: =(Assumptions!$B$7*((Assumptions!$B$6*Assumptions!$B$5)*((Assumptions!$B$6*Assumptions!$B$5)+1)/2)*((D$13)^2-($A17)^2)+Assumptions!$B$9/10000*Assumptions!$B$8*Assumptions!$B$4*Assumptions!$B$7-(Assumptions!$B$7-1)*Assumptions!$B$10-Assumptions!$B$11+Assumptions!$B$7*Assumptions!$B$12)+Assumptions!$B$13*(1-Assumptions!$B$14*$A17) | E17: =(Assumptions!$B$7*((Assumptions!$B$6*Assumptions!$B$5)*((Assumptions!$B$6*Assumptions!$B$5)+1)/2)*((E$13)^2-($A17)^2)+Assumptions!$B$9/10000*Assumptions!$B$8*Assumptions!$B$4*Assumptions!$B$7-(Assumptions!$B$7-1)*Assumptions!$B$10-Assumptions!$B$11+Assumptions!$B$7*Assumptions!$B$12)+Assumptions!$B$13*(1-Assumptions!$B$14*$A17) | F17: =(Assumptions!$B$7*((Assumptions!$B$6*Assumptions!$B$5)*((Assumptions!$B$6*Assumptions!$B$5)+1)/2)*((F$13)^2-($A17)^2)+Assumptions!$B$9/10000*Assumptions!$B$8*Assumptions!$B$4*Assumptions!$B$7-(Assumptions!$B$7-1)*Assumptions!$B$10-Assumptions!$B$11+Assumptions!$B$7*Assumptions!$B$12)+Assumptions!$B$13*(1-Assumptions!$B$14*$A17)
A18: =Assumptions!F$16 | B18: =(Assumptions!$B$7*((Assumptions!$B$6*Assumptions!$B$5)*((Assumptions!$B$6*Assumptions!$B$5)+1)/2)*((B$13)^2-($A18)^2)+Assumptions!$B$9/10000*Assumptions!$B$8*Assumptions!$B$4*Assumptions!$B$7-(Assumptions!$B$7-1)*Assumptions!$B$10-Assumptions!$B$11+Assumptions!$B$7*Assumptions!$B$12)+Assumptions!$B$13*(1-Assumptions!$B$14*$A18) | C18: =(Assumptions!$B$7*((Assumptions!$B$6*Assumptions!$B$5)*((Assumptions!$B$6*Assumptions!$B$5)+1)/2)*((C$13)^2-($A18)^2)+Assumptions!$B$9/10000*Assumptions!$B$8*Assumptions!$B$4*Assumptions!$B$7-(Assumptions!$B$7-1)*Assumptions!$B$10-Assumptions!$B$11+Assumptions!$B$7*Assumptions!$B$12)+Assumptions!$B$13*(1-Assumptions!$B$14*$A18) | D18: =(Assumptions!$B$7*((Assumptions!$B$6*Assumptions!$B$5)*((Assumptions!$B$6*Assumptions!$B$5)+1)/2)*((D$13)^2-($A18)^2)+Assumptions!$B$9/10000*Assumptions!$B$8*Assumptions!$B$4*Assumptions!$B$7-(Assumptions!$B$7-1)*Assumptions!$B$10-Assumptions!$B$11+Assumptions!$B$7*Assumptions!$B$12)+Assumptions!$B$13*(1-Assumptions!$B$14*$A18) | E18: =(Assumptions!$B$7*((Assumptions!$B$6*Assumptions!$B$5)*((Assumptions!$B$6*Assumptions!$B$5)+1)/2)*((E$13)^2-($A18)^2)+Assumptions!$B$9/10000*Assumptions!$B$8*Assumptions!$B$4*Assumptions!$B$7-(Assumptions!$B$7-1)*Assumptions!$B$10-Assumptions!$B$11+Assumptions!$B$7*Assumptions!$B$12)+Assumptions!$B$13*(1-Assumptions!$B$14*$A18) | F18: =(Assumptions!$B$7*((Assumptions!$B$6*Assumptions!$B$5)*((Assumptions!$B$6*Assumptions!$B$5)+1)/2)*((F$13)^2-($A18)^2)+Assumptions!$B$9/10000*Assumptions!$B$8*Assumptions!$B$4*Assumptions!$B$7-(Assumptions!$B$7-1)*Assumptions!$B$10-Assumptions!$B$11+Assumptions!$B$7*Assumptions!$B$12)+Assumptions!$B$13*(1-Assumptions!$B$14*$A18)
A21: LP wins where calibration vol > realized vol (calmer than you priced); loses in spikes. m amplifies BOTH (bigger G). Magnitudes illustrative.

Sheet Scenario_calc
A1: SINGLE-SCENARIO BREAKDOWN (edit yellow: RV, sigma_cal)
A3: realized_vol RV | B3: 0.6
A4: sigma_cal (calibration vol) | B4: 0.7
A6: G = (m*gamma)(m*gamma+1)/2 | B6: =((Assumptions!$B$6*Assumptions!$B$5)*((Assumptions!$B$6*Assumptions!$B$5)+1)/2)
A7: options_net (carry - gamma bleed) | B7: =Assumptions!$B$7*((Assumptions!$B$6*Assumptions!$B$5)*((Assumptions!$B$6*Assumptions!$B$5)+1)/2)*($B$4^2-$B$3^2)
A8: Fee income | B8: =Assumptions!$B$9/10000*Assumptions!$B$8*Assumptions!$B$4*Assumptions!$B$7
A9: Financing | B9: =-(Assumptions!$B$7-1)*Assumptions!$B$10
A10: Hedge (fee+funding) | B10: =-Assumptions!$B$11+Assumptions!$B$7*Assumptions!$B$12
A11: BASE net (dollar margin) | B11: =B7+B8+B9+B10
A12: HLP layer | B12: =Assumptions!$B$13*(1-Assumptions!$B$14*$B$3)
A13: RESTAKED net (HLP margin) | B13: =B11+B12
